{"modules": [{"img": 1, "x": 14, "y": 6, "w": 18, "h": 13}, {"img": 1, "x": 2, "y": 0, "w": 9, "h": 31}, {"img": 1, "x": 2, "y": 34, "w": 30, "h": 29}, {"img": 0, "x": 0, "y": 0, "w": 23, "h": 23}, {"img": 0, "x": 23, "y": 0, "w": 40, "h": 23}, {"img": 0, "x": 21, "y": 23, "w": 35, "h": 15}, {"img": 0, "x": 3, "y": 23, "w": 3, "h": 31}, {"img": 0, "x": 11, "y": 23, "w": 3, "h": 30}, {"img": 0, "x": 24, "y": 42, "w": 33, "h": 20}, {"img": 0, "x": 0, "y": 54, "w": 14, "h": 62}, {"img": 0, "x": 70, "y": 0, "w": 70, "h": 31}, {"img": 0, "x": 65, "y": 31, "w": 80, "h": 39}, {"img": 0, "x": 52, "y": 70, "w": 55, "h": 36}, {"img": 0, "x": 107, "y": 70, "w": 39, "h": 42}, {"img": 0, "x": 145, "y": 0, "w": 126, "h": 39}, {"img": 0, "x": 249, "y": 160, "w": 30, "h": 30}, {"img": 0, "x": 279, "y": 160, "w": 14, "h": 14}, {"img": 0, "x": 279, "y": 174, "w": 11, "h": 10}, {"img": 0, "x": 279, "y": 184, "w": 3, "h": 3}, {"img": 0, "x": 253, "y": 193, "w": 30, "h": 2}, {"img": 0, "x": 146, "y": 84, "w": 9, "h": 15}, {"img": 0, "x": 155, "y": 84, "w": 16, "h": 10}, {"img": 0, "x": 146, "y": 41, "w": 35, "h": 43}, {"img": 0, "x": 181, "y": 41, "w": 51, "h": 61}, {"img": 0, "x": 171, "y": 102, "w": 46, "h": 42}, {"img": 0, "x": 146, "y": 99, "w": 11, "h": 21}, {"img": 0, "x": 157, "y": 94, "w": 14, "h": 30}, {"img": 0, "x": 233, "y": 42, "w": 60, "h": 74}, {"img": 0, "x": 221, "y": 119, "w": 44, "h": 32}, {"img": 0, "x": 53, "y": 112, "w": 89, "h": 47}, {"img": 0, "x": 0, "y": 124, "w": 52, "h": 61}, {"img": 0, "x": 52, "y": 159, "w": 70, "h": 21}, {"img": 0, "x": 146, "y": 151, "w": 103, "h": 39}, {"img": 0, "x": 0, "y": 185, "w": 116, "h": 39}, {"img": 0, "x": 116, "y": 190, "w": 122, "h": 38}, {"img": 0, "x": 15, "y": 54, "w": 9, "h": 58}, {"img": 0, "x": 6, "y": 23, "w": 3, "h": 31}, {"img": 0, "x": 0, "y": 23, "w": 3, "h": 31}, {"img": 2, "x": 0, "y": 66, "w": 69, "h": 66}], "frames": [[{"module": 3, "dx": -15, "dy": -66, "flip": 0}], [{"module": 4, "dx": -22, "dy": -78, "flip": 0}, {"module": 5, "dx": -24, "dy": -55, "flip": 0}], [{"module": 10, "dx": -39, "dy": -93, "flip": 4}, {"module": 11, "dx": -42, "dy": -64, "flip": 4}, {"module": 3, "dx": 20, "dy": -48, "flip": 0}], [{"module": 4, "dx": 13, "dy": -59, "flip": 0}, {"module": 5, "dx": 11, "dy": -36, "flip": 0}], [{"module": 10, "dx": -3, "dy": -80, "flip": 0}, {"module": 11, "dx": -5, "dy": -52, "flip": 0}], [{"module": 24, "dx": -9, "dy": -31, "flip": 0}], [{"module": 24, "dx": -25, "dy": -32, "flip": 0}, {"module": 24, "dx": -9, "dy": -31, "flip": 0}], [{"module": 24, "dx": -25, "dy": -32, "flip": 0}, {"module": 24, "dx": -9, "dy": -31, "flip": 0}, {"module": 19, "dx": 12, "dy": -34, "flip": 0}, {"module": 16, "dx": 20, "dy": -40, "flip": 0}], [{"module": 24, "dx": -25, "dy": -32, "flip": 0}, {"module": 24, "dx": -9, "dy": -31, "flip": 0}, {"module": 13, "dx": 10, "dy": -55, "flip": 0}, {"module": 19, "dx": -18, "dy": -17, "flip": 0}, {"module": 19, "dx": -24, "dy": -39, "flip": 0}, {"module": 17, "dx": -8, "dy": -21, "flip": 0}, {"module": 17, "dx": -15, "dy": -43, "flip": 0}], [{"module": 24, "dx": -25, "dy": -32, "flip": 0}, {"module": 24, "dx": -9, "dy": -31, "flip": 0}, {"module": 13, "dx": -17, "dy": -67, "flip": 0}, {"module": 13, "dx": -23, "dy": -37, "flip": 0}, {"module": 30, "dx": 0, "dy": -73, "flip": 0}], [{"module": 24, "dx": -25, "dy": -32, "flip": 0}, {"module": 24, "dx": -9, "dy": -31, "flip": 0}, {"module": 30, "dx": -35, "dy": -87, "flip": 0}, {"module": 30, "dx": -31, "dy": -53, "flip": 0}], [], [{"module": 2, "dx": -8, "dy": -20, "flip": 0}, {"module": 2, "dx": -7, "dy": -39, "flip": 0}, {"module": 2, "dx": -6, "dy": -58, "flip": 0}, {"module": 2, "dx": -30, "dy": -53, "flip": 0}, {"module": 2, "dx": -26, "dy": -35, "flip": 0}, {"module": 2, "dx": -34, "dy": -16, "flip": 0}, {"module": 2, "dx": 18, "dy": -48, "flip": 0}, {"module": 2, "dx": 17, "dy": -30, "flip": 0}, {"module": 2, "dx": 14, "dy": -12, "flip": 0}], [{"module": 2, "dx": -9, "dy": -11, "flip": 0}, {"module": 2, "dx": -7, "dy": -39, "flip": 0}, {"module": 2, "dx": -5, "dy": -59, "flip": 0}, {"module": 2, "dx": -30, "dy": -58, "flip": 0}, {"module": 2, "dx": -37, "dy": -32, "flip": 0}, {"module": 2, "dx": -39, "dy": -12, "flip": 0}, {"module": 2, "dx": 25, "dy": -54, "flip": 0}, {"module": 2, "dx": 27, "dy": -31, "flip": 0}, {"module": 2, "dx": 17, "dy": -9, "flip": 0}], [{"module": 2, "dx": -8, "dy": -3, "flip": 0}, {"module": 2, "dx": -6, "dy": -35, "flip": 0}, {"module": 2, "dx": 6, "dy": -67, "flip": 0}, {"module": 2, "dx": -23, "dy": -64, "flip": 0}, {"module": 2, "dx": -40, "dy": -44, "flip": 0}, {"module": 2, "dx": -33, "dy": -17, "flip": 0}, {"module": 2, "dx": 29, "dy": -53, "flip": 0}, {"module": 2, "dx": 35, "dy": -31, "flip": 0}, {"module": 2, "dx": 21, "dy": -10, "flip": 0}], [{"module": 2, "dx": -5, "dy": 6, "flip": 0}, {"module": 2, "dx": -6, "dy": -36, "flip": 0}, {"module": 2, "dx": -2, "dy": -78, "flip": 0}, {"module": 2, "dx": -44, "dy": -84, "flip": 0}, {"module": 2, "dx": -63, "dy": -55, "flip": 0}, {"module": 2, "dx": -45, "dy": -11, "flip": 0}, {"module": 2, "dx": 41, "dy": -68, "flip": 0}, {"module": 2, "dx": 49, "dy": -31, "flip": 0}, {"module": 2, "dx": 37, "dy": -4, "flip": 0}], [{"module": 2, "dx": -15, "dy": 19, "flip": 0}, {"module": 2, "dx": -12, "dy": -42, "flip": 0}, {"module": 2, "dx": -2, "dy": -96, "flip": 0}, {"module": 2, "dx": -49, "dy": -89, "flip": 0}, {"module": 2, "dx": -68, "dy": -48, "flip": 0}, {"module": 2, "dx": -58, "dy": -3, "flip": 0}, {"module": 2, "dx": 52, "dy": -79, "flip": 0}, {"module": 2, "dx": 51, "dy": -33, "flip": 0}, {"module": 2, "dx": 39, "dy": 11, "flip": 0}], [{"module": 14, "dx": -52, "dy": -141, "flip": 0}], [{"module": 14, "dx": -52, "dy": -117, "flip": 0}, {"module": 14, "dx": -48, "dy": -152, "flip": 4}], [{"module": 14, "dx": -52, "dy": -84, "flip": 0}, {"module": 14, "dx": -48, "dy": -119, "flip": 4}, {"module": 14, "dx": -79, "dy": -153, "flip": 0}], [{"module": 14, "dx": -52, "dy": -64, "flip": 0}, {"module": 14, "dx": -48, "dy": -99, "flip": 4}, {"module": 14, "dx": -79, "dy": -133, "flip": 0}, {"module": 14, "dx": -14, "dy": -171, "flip": 0}], [{"module": 14, "dx": -52, "dy": -36, "flip": 0}, {"module": 14, "dx": -48, "dy": -71, "flip": 4}, {"module": 14, "dx": -79, "dy": -105, "flip": 0}, {"module": 14, "dx": -14, "dy": -143, "flip": 0}, {"module": 14, "dx": -127, "dy": -178, "flip": 4}, {"module": 38, "dx": 8, "dy": -112, "flip": 0}], [{"module": 14, "dx": -52, "dy": -4, "flip": 0}, {"module": 14, "dx": -48, "dy": -39, "flip": 4}, {"module": 14, "dx": -79, "dy": -73, "flip": 0}, {"module": 14, "dx": -14, "dy": -111, "flip": 0}, {"module": 14, "dx": -127, "dy": -146, "flip": 4}, {"module": 14, "dx": -43, "dy": -165, "flip": 4}, {"module": 38, "dx": -9, "dy": -96, "flip": 0}], [{"module": 14, "dx": -52, "dy": 28, "flip": 0}, {"module": 14, "dx": -48, "dy": -7, "flip": 4}, {"module": 14, "dx": -79, "dy": -41, "flip": 0}, {"module": 14, "dx": -14, "dy": -79, "flip": 0}, {"module": 14, "dx": -127, "dy": -114, "flip": 4}, {"module": 14, "dx": -43, "dy": -133, "flip": 4}, {"module": 14, "dx": -110, "dy": -160, "flip": 0}, {"module": 14, "dx": -60, "dy": -185, "flip": 4}, {"module": 38, "dx": -25, "dy": -74, "flip": 0}], [{"module": 14, "dx": -52, "dy": 46, "flip": 0}, {"module": 14, "dx": -48, "dy": 11, "flip": 4}, {"module": 14, "dx": -79, "dy": -23, "flip": 0}, {"module": 14, "dx": -14, "dy": -61, "flip": 0}, {"module": 14, "dx": -127, "dy": -96, "flip": 4}, {"module": 14, "dx": -43, "dy": -115, "flip": 4}, {"module": 14, "dx": -110, "dy": -142, "flip": 0}, {"module": 14, "dx": -60, "dy": -167, "flip": 4}, {"module": 14, "dx": -61, "dy": -194, "flip": 0}, {"module": 38, "dx": -40, "dy": -44, "flip": 0}], [{"module": 9, "dx": -41, "dy": -176, "flip": 0}, {"module": 9, "dx": -5, "dy": -168, "flip": 4}, {"module": 35, "dx": 17, "dy": -167, "flip": 0}, {"module": 7, "dx": -17, "dy": -171, "flip": 0}, {"module": 35, "dx": -57, "dy": -149, "flip": 0}, {"module": 7, "dx": 29, "dy": -127, "flip": 0}, {"module": 35, "dx": 37, "dy": -140, "flip": 4}], [{"module": 9, "dx": -41, "dy": -130, "flip": 0}, {"module": 9, "dx": -5, "dy": -122, "flip": 4}, {"module": 35, "dx": 17, "dy": -121, "flip": 0}, {"module": 7, "dx": -17, "dy": -125, "flip": 0}, {"module": 35, "dx": -57, "dy": -103, "flip": 0}, {"module": 7, "dx": 29, "dy": -81, "flip": 0}, {"module": 35, "dx": 37, "dy": -94, "flip": 4}], [{"module": 9, "dx": -41, "dy": -103, "flip": 0}, {"module": 9, "dx": -5, "dy": -95, "flip": 4}, {"module": 35, "dx": 17, "dy": -94, "flip": 0}, {"module": 7, "dx": -17, "dy": -98, "flip": 0}, {"module": 35, "dx": -57, "dy": -76, "flip": 0}, {"module": 7, "dx": 29, "dy": -54, "flip": 0}, {"module": 35, "dx": 37, "dy": -67, "flip": 4}], [{"module": 9, "dx": -41, "dy": -59, "flip": 0}, {"module": 9, "dx": -5, "dy": -51, "flip": 4}, {"module": 35, "dx": 17, "dy": -50, "flip": 0}, {"module": 7, "dx": -17, "dy": -54, "flip": 0}, {"module": 35, "dx": -57, "dy": -32, "flip": 0}, {"module": 7, "dx": 29, "dy": -10, "flip": 0}, {"module": 35, "dx": 37, "dy": -23, "flip": 4}], [{"module": 8, "dx": -15, "dy": -16, "flip": 0}], [{"module": 12, "dx": -27, "dy": -28, "flip": 0}], [{"module": 29, "dx": -46, "dy": -39, "flip": 0}, {"module": 12, "dx": -27, "dy": -28, "flip": 0}], [{"module": 1, "dx": -19, "dy": -43, "flip": 0}, {"module": 1, "dx": 5, "dy": -43, "flip": 4}, {"module": 1, "dx": -19, "dy": -74, "flip": 0}, {"module": 1, "dx": 5, "dy": -74, "flip": 4}, {"module": 18, "dx": -32, "dy": -40, "flip": 0}, {"module": 18, "dx": -25, "dy": -29, "flip": 0}, {"module": 18, "dx": -40, "dy": -20, "flip": 0}, {"module": 18, "dx": -26, "dy": -10, "flip": 0}, {"module": 18, "dx": -10, "dy": -17, "flip": 0}, {"module": 18, "dx": -17, "dy": -40, "flip": 0}, {"module": 18, "dx": 12, "dy": -30, "flip": 0}, {"module": 18, "dx": 19, "dy": -48, "flip": 0}, {"module": 18, "dx": 25, "dy": -29, "flip": 0}, {"module": 18, "dx": 21, "dy": -21, "flip": 0}, {"module": 18, "dx": 20, "dy": -7, "flip": 0}, {"module": 18, "dx": 43, "dy": -20, "flip": 0}, {"module": 18, "dx": 28, "dy": -2, "flip": 0}, {"module": 37, "dx": -10, "dy": -74, "flip": 0}, {"module": 37, "dx": -10, "dy": -43, "flip": 0}, {"module": 6, "dx": -7, "dy": -74, "flip": 0}, {"module": 37, "dx": -7, "dy": -43, "flip": 0}, {"module": 37, "dx": 2, "dy": -74, "flip": 0}, {"module": 37, "dx": 2, "dy": -43, "flip": 0}, {"module": 6, "dx": -1, "dy": -74, "flip": 0}, {"module": 6, "dx": -1, "dy": -43, "flip": 0}, {"module": 36, "dx": -4, "dy": -74, "flip": 0}, {"module": 36, "dx": -4, "dy": -43, "flip": 0}, {"module": 6, "dx": -7, "dy": -43, "flip": 0}, {"module": 12, "dx": -28, "dy": -28, "flip": 0}], [{"module": 1, "dx": -22, "dy": -43, "flip": 0}, {"module": 1, "dx": 14, "dy": -43, "flip": 4}, {"module": 1, "dx": -22, "dy": -74, "flip": 0}, {"module": 1, "dx": 14, "dy": -74, "flip": 4}, {"module": 18, "dx": -55, "dy": -48, "flip": 0}, {"module": 18, "dx": -28, "dy": -27, "flip": 0}, {"module": 18, "dx": -51, "dy": -17, "flip": 0}, {"module": 18, "dx": -29, "dy": -16, "flip": 0}, {"module": 18, "dx": -9, "dy": -17, "flip": 0}, {"module": 18, "dx": -37, "dy": -67, "flip": 0}, {"module": 18, "dx": 12, "dy": -37, "flip": 0}, {"module": 18, "dx": 32, "dy": -58, "flip": 0}, {"module": 18, "dx": 47, "dy": -26, "flip": 0}, {"module": 18, "dx": 27, "dy": -25, "flip": 0}, {"module": 18, "dx": 21, "dy": -7, "flip": 0}, {"module": 18, "dx": 57, "dy": -46, "flip": 0}, {"module": 18, "dx": 43, "dy": -10, "flip": 0}, {"module": 37, "dx": -13, "dy": -74, "flip": 0}, {"module": 37, "dx": -13, "dy": -43, "flip": 0}, {"module": 6, "dx": -10, "dy": -74, "flip": 0}, {"module": 6, "dx": -10, "dy": -43, "flip": 0}, {"module": 37, "dx": 11, "dy": -74, "flip": 0}, {"module": 37, "dx": 11, "dy": -43, "flip": 0}, {"module": 6, "dx": 8, "dy": -74, "flip": 0}, {"module": 6, "dx": 8, "dy": -43, "flip": 0}, {"module": 36, "dx": -7, "dy": -74, "flip": 0}, {"module": 36, "dx": -7, "dy": -43, "flip": 0}, {"module": 36, "dx": 5, "dy": -74, "flip": 0}, {"module": 36, "dx": 5, "dy": -43, "flip": 0}, {"module": 36, "dx": -4, "dy": -74, "flip": 0}, {"module": 36, "dx": 2, "dy": -74, "flip": 0}, {"module": 36, "dx": 2, "dy": -43, "flip": 0}, {"module": 36, "dx": -4, "dy": -43, "flip": 0}, {"module": 36, "dx": -1, "dy": -74, "flip": 0}, {"module": 36, "dx": -1, "dy": -43, "flip": 0}, {"module": 12, "dx": -28, "dy": -34, "flip": 4}, {"module": 1, "dx": -22, "dy": -105, "flip": 0}, {"module": 1, "dx": 14, "dy": -105, "flip": 4}, {"module": 37, "dx": -13, "dy": -105, "flip": 0}, {"module": 6, "dx": -10, "dy": -105, "flip": 0}, {"module": 37, "dx": 11, "dy": -105, "flip": 0}, {"module": 6, "dx": 8, "dy": -105, "flip": 0}, {"module": 36, "dx": -7, "dy": -105, "flip": 0}, {"module": 36, "dx": 5, "dy": -105, "flip": 0}, {"module": 36, "dx": -4, "dy": -105, "flip": 0}, {"module": 36, "dx": 2, "dy": -105, "flip": 0}, {"module": 36, "dx": -1, "dy": -105, "flip": 0}, {"module": 1, "dx": -22, "dy": -136, "flip": 0}, {"module": 1, "dx": 14, "dy": -136, "flip": 4}, {"module": 37, "dx": -13, "dy": -136, "flip": 0}, {"module": 6, "dx": -10, "dy": -136, "flip": 0}, {"module": 37, "dx": 11, "dy": -136, "flip": 0}, {"module": 6, "dx": 8, "dy": -136, "flip": 0}, {"module": 36, "dx": -7, "dy": -136, "flip": 0}, {"module": 36, "dx": 5, "dy": -136, "flip": 0}, {"module": 36, "dx": -4, "dy": -136, "flip": 0}, {"module": 36, "dx": 2, "dy": -136, "flip": 0}, {"module": 36, "dx": -1, "dy": -136, "flip": 0}], [{"module": 1, "dx": -24, "dy": -43, "flip": 0}, {"module": 1, "dx": 15, "dy": -43, "flip": 4}, {"module": 1, "dx": -24, "dy": -74, "flip": 0}, {"module": 1, "dx": 15, "dy": -74, "flip": 4}, {"module": 18, "dx": -46, "dy": -36, "flip": 0}, {"module": 18, "dx": -30, "dy": -27, "flip": 0}, {"module": 18, "dx": -42, "dy": -13, "flip": 0}, {"module": 18, "dx": -31, "dy": -16, "flip": 0}, {"module": 18, "dx": -11, "dy": -17, "flip": 0}, {"module": 18, "dx": -23, "dy": -42, "flip": 0}, {"module": 18, "dx": 13, "dy": -37, "flip": 0}, {"module": 18, "dx": 41, "dy": -111, "flip": 0}, {"module": 18, "dx": 32, "dy": -31, "flip": 0}, {"module": 18, "dx": 28, "dy": -25, "flip": 0}, {"module": 18, "dx": 22, "dy": -7, "flip": 0}, {"module": 18, "dx": 70, "dy": -77, "flip": 0}, {"module": 18, "dx": 37, "dy": -4, "flip": 0}, {"module": 37, "dx": -15, "dy": -74, "flip": 0}, {"module": 37, "dx": -15, "dy": -43, "flip": 0}, {"module": 6, "dx": -12, "dy": -74, "flip": 0}, {"module": 6, "dx": -12, "dy": -43, "flip": 0}, {"module": 37, "dx": 12, "dy": -74, "flip": 0}, {"module": 37, "dx": 12, "dy": -43, "flip": 0}, {"module": 6, "dx": 9, "dy": -74, "flip": 0}, {"module": 6, "dx": 9, "dy": -43, "flip": 0}, {"module": 36, "dx": -9, "dy": -74, "flip": 0}, {"module": 36, "dx": -9, "dy": -43, "flip": 0}, {"module": 36, "dx": 6, "dy": -74, "flip": 0}, {"module": 36, "dx": 6, "dy": -43, "flip": 0}, {"module": 36, "dx": -6, "dy": -74, "flip": 0}, {"module": 36, "dx": 3, "dy": -74, "flip": 0}, {"module": 36, "dx": 3, "dy": -43, "flip": 0}, {"module": 36, "dx": -6, "dy": -43, "flip": 0}, {"module": 36, "dx": 0, "dy": -43, "flip": 0}, {"module": 36, "dx": -3, "dy": -74, "flip": 0}, {"module": 36, "dx": -3, "dy": -43, "flip": 0}, {"module": 29, "dx": -48, "dy": -40, "flip": 0}, {"module": 12, "dx": -29, "dy": -29, "flip": 4}, {"module": 1, "dx": -24, "dy": -105, "flip": 0}, {"module": 1, "dx": 15, "dy": -105, "flip": 4}, {"module": 37, "dx": -15, "dy": -105, "flip": 0}, {"module": 6, "dx": -12, "dy": -105, "flip": 0}, {"module": 37, "dx": 12, "dy": -105, "flip": 0}, {"module": 6, "dx": 9, "dy": -105, "flip": 0}, {"module": 36, "dx": -9, "dy": -105, "flip": 0}, {"module": 36, "dx": 6, "dy": -105, "flip": 0}, {"module": 36, "dx": -6, "dy": -105, "flip": 0}, {"module": 36, "dx": 3, "dy": -105, "flip": 0}, {"module": 36, "dx": -3, "dy": -105, "flip": 0}, {"module": 1, "dx": -24, "dy": -136, "flip": 0}, {"module": 1, "dx": 15, "dy": -136, "flip": 4}, {"module": 37, "dx": -15, "dy": -136, "flip": 0}, {"module": 6, "dx": -12, "dy": -136, "flip": 0}, {"module": 37, "dx": 12, "dy": -136, "flip": 0}, {"module": 6, "dx": 9, "dy": -136, "flip": 0}, {"module": 36, "dx": -9, "dy": -136, "flip": 0}, {"module": 36, "dx": 6, "dy": -136, "flip": 0}, {"module": 36, "dx": -6, "dy": -136, "flip": 0}, {"module": 36, "dx": 3, "dy": -136, "flip": 0}, {"module": 36, "dx": -3, "dy": -136, "flip": 0}, {"module": 18, "dx": -32, "dy": -85, "flip": 0}, {"module": 18, "dx": -62, "dy": -86, "flip": 0}, {"module": 18, "dx": 31, "dy": -62, "flip": 0}, {"module": 18, "dx": 63, "dy": -45, "flip": 0}, {"module": 18, "dx": 69, "dy": -89, "flip": 0}, {"module": 18, "dx": -42, "dy": -96, "flip": 0}, {"module": 18, "dx": -14, "dy": -85, "flip": 0}, {"module": 18, "dx": 8, "dy": -53, "flip": 0}, {"module": 18, "dx": -57, "dy": -52, "flip": 0}, {"module": 36, "dx": 0, "dy": -136, "flip": 0}, {"module": 36, "dx": 0, "dy": -105, "flip": 0}, {"module": 36, "dx": 0, "dy": -74, "flip": 0}], [{"module": 1, "dx": -27, "dy": -43, "flip": 0}, {"module": 1, "dx": 18, "dy": -43, "flip": 4}, {"module": 1, "dx": -27, "dy": -74, "flip": 0}, {"module": 1, "dx": 18, "dy": -74, "flip": 4}, {"module": 18, "dx": -46, "dy": -36, "flip": 0}, {"module": 18, "dx": -33, "dy": -27, "flip": 0}, {"module": 18, "dx": -42, "dy": -13, "flip": 0}, {"module": 18, "dx": -34, "dy": -16, "flip": 0}, {"module": 18, "dx": -14, "dy": -17, "flip": 0}, {"module": 18, "dx": -26, "dy": -42, "flip": 0}, {"module": 18, "dx": 16, "dy": -37, "flip": 0}, {"module": 18, "dx": 35, "dy": -101, "flip": 0}, {"module": 18, "dx": 35, "dy": -31, "flip": 0}, {"module": 18, "dx": 31, "dy": -25, "flip": 0}, {"module": 18, "dx": 25, "dy": -7, "flip": 0}, {"module": 18, "dx": 48, "dy": -133, "flip": 0}, {"module": 18, "dx": 40, "dy": -4, "flip": 0}, {"module": 37, "dx": -18, "dy": -74, "flip": 0}, {"module": 37, "dx": -18, "dy": -43, "flip": 0}, {"module": 37, "dx": 15, "dy": -74, "flip": 0}, {"module": 37, "dx": 15, "dy": -43, "flip": 0}, {"module": 36, "dx": -9, "dy": -74, "flip": 0}, {"module": 36, "dx": 6, "dy": -74, "flip": 0}, {"module": 36, "dx": 6, "dy": -43, "flip": 0}, {"module": 36, "dx": -9, "dy": -43, "flip": 0}, {"module": 36, "dx": 3, "dy": -43, "flip": 0}, {"module": 36, "dx": -6, "dy": -74, "flip": 0}, {"module": 36, "dx": 0, "dy": -43, "flip": 0}, {"module": 36, "dx": -3, "dy": -43, "flip": 0}, {"module": 36, "dx": -6, "dy": -43, "flip": 0}, {"module": 1, "dx": -27, "dy": -105, "flip": 0}, {"module": 1, "dx": 18, "dy": -105, "flip": 4}, {"module": 37, "dx": -18, "dy": -105, "flip": 0}, {"module": 37, "dx": 15, "dy": -105, "flip": 0}, {"module": 36, "dx": -9, "dy": -105, "flip": 0}, {"module": 36, "dx": 6, "dy": -105, "flip": 0}, {"module": 36, "dx": -6, "dy": -105, "flip": 0}, {"module": 1, "dx": -27, "dy": -136, "flip": 0}, {"module": 1, "dx": 18, "dy": -136, "flip": 4}, {"module": 37, "dx": -18, "dy": -136, "flip": 0}, {"module": 37, "dx": 15, "dy": -136, "flip": 0}, {"module": 36, "dx": -9, "dy": -136, "flip": 0}, {"module": 36, "dx": 6, "dy": -136, "flip": 0}, {"module": 36, "dx": -6, "dy": -136, "flip": 0}, {"module": 18, "dx": -31, "dy": -117, "flip": 0}, {"module": 18, "dx": -40, "dy": -88, "flip": 0}, {"module": 18, "dx": 47, "dy": -69, "flip": 0}, {"module": 18, "dx": 63, "dy": -45, "flip": 0}, {"module": 18, "dx": 70, "dy": -105, "flip": 0}, {"module": 18, "dx": -49, "dy": -115, "flip": 0}, {"module": 18, "dx": -17, "dy": -85, "flip": 0}, {"module": 18, "dx": 11, "dy": -53, "flip": 0}, {"module": 18, "dx": -27, "dy": -68, "flip": 0}, {"module": 36, "dx": 3, "dy": -136, "flip": 0}, {"module": 36, "dx": 3, "dy": -105, "flip": 0}, {"module": 36, "dx": 3, "dy": -74, "flip": 0}, {"module": 36, "dx": -3, "dy": -136, "flip": 0}, {"module": 36, "dx": 0, "dy": -136, "flip": 0}, {"module": 36, "dx": -3, "dy": -105, "flip": 0}, {"module": 36, "dx": 0, "dy": -105, "flip": 0}, {"module": 36, "dx": -3, "dy": -74, "flip": 0}, {"module": 36, "dx": 0, "dy": -74, "flip": 0}, {"module": 37, "dx": -15, "dy": -136, "flip": 0}, {"module": 37, "dx": -15, "dy": -105, "flip": 0}, {"module": 37, "dx": -15, "dy": -74, "flip": 0}, {"module": 37, "dx": -15, "dy": -43, "flip": 0}, {"module": 37, "dx": 12, "dy": -136, "flip": 0}, {"module": 37, "dx": 12, "dy": -105, "flip": 0}, {"module": 37, "dx": 12, "dy": -74, "flip": 0}, {"module": 37, "dx": 12, "dy": -43, "flip": 0}, {"module": 6, "dx": -12, "dy": -136, "flip": 0}, {"module": 6, "dx": -12, "dy": -105, "flip": 0}, {"module": 6, "dx": -12, "dy": -74, "flip": 0}, {"module": 6, "dx": -12, "dy": -43, "flip": 0}, {"module": 6, "dx": 9, "dy": -136, "flip": 0}, {"module": 6, "dx": 9, "dy": -105, "flip": 0}, {"module": 6, "dx": 9, "dy": -74, "flip": 0}, {"module": 6, "dx": 9, "dy": -43, "flip": 0}, {"module": 29, "dx": -48, "dy": -40, "flip": 0}, {"module": 12, "dx": -29, "dy": -29, "flip": 4}], [{"module": 1, "dx": -27, "dy": -43, "flip": 0}, {"module": 1, "dx": 18, "dy": -43, "flip": 4}, {"module": 1, "dx": -27, "dy": -74, "flip": 0}, {"module": 1, "dx": 18, "dy": -74, "flip": 4}, {"module": 18, "dx": -46, "dy": -36, "flip": 0}, {"module": 18, "dx": -33, "dy": -27, "flip": 0}, {"module": 18, "dx": -42, "dy": -13, "flip": 0}, {"module": 18, "dx": -34, "dy": -16, "flip": 0}, {"module": 18, "dx": -14, "dy": -17, "flip": 0}, {"module": 18, "dx": -26, "dy": -42, "flip": 0}, {"module": 18, "dx": 16, "dy": -37, "flip": 0}, {"module": 18, "dx": 35, "dy": -101, "flip": 0}, {"module": 18, "dx": 35, "dy": -31, "flip": 0}, {"module": 18, "dx": 31, "dy": -25, "flip": 0}, {"module": 18, "dx": 25, "dy": -7, "flip": 0}, {"module": 18, "dx": 48, "dy": -133, "flip": 0}, {"module": 18, "dx": 40, "dy": -4, "flip": 0}, {"module": 37, "dx": -18, "dy": -74, "flip": 0}, {"module": 37, "dx": -18, "dy": -43, "flip": 0}, {"module": 37, "dx": 15, "dy": -74, "flip": 0}, {"module": 37, "dx": 15, "dy": -43, "flip": 0}, {"module": 36, "dx": -9, "dy": -74, "flip": 0}, {"module": 36, "dx": 6, "dy": -74, "flip": 0}, {"module": 36, "dx": 6, "dy": -43, "flip": 0}, {"module": 36, "dx": -9, "dy": -43, "flip": 0}, {"module": 36, "dx": 3, "dy": -43, "flip": 0}, {"module": 36, "dx": -6, "dy": -74, "flip": 0}, {"module": 36, "dx": 0, "dy": -43, "flip": 0}, {"module": 36, "dx": -3, "dy": -43, "flip": 0}, {"module": 36, "dx": -6, "dy": -43, "flip": 0}, {"module": 1, "dx": -27, "dy": -105, "flip": 0}, {"module": 1, "dx": 18, "dy": -105, "flip": 4}, {"module": 37, "dx": -18, "dy": -105, "flip": 0}, {"module": 37, "dx": 15, "dy": -105, "flip": 0}, {"module": 36, "dx": -9, "dy": -105, "flip": 0}, {"module": 36, "dx": 6, "dy": -105, "flip": 0}, {"module": 36, "dx": -6, "dy": -105, "flip": 0}, {"module": 1, "dx": -27, "dy": -136, "flip": 0}, {"module": 1, "dx": 18, "dy": -136, "flip": 4}, {"module": 37, "dx": -18, "dy": -136, "flip": 0}, {"module": 37, "dx": 15, "dy": -136, "flip": 0}, {"module": 36, "dx": -9, "dy": -136, "flip": 0}, {"module": 36, "dx": 6, "dy": -136, "flip": 0}, {"module": 36, "dx": -6, "dy": -136, "flip": 0}, {"module": 18, "dx": -31, "dy": -117, "flip": 0}, {"module": 18, "dx": -40, "dy": -88, "flip": 0}, {"module": 18, "dx": 47, "dy": -69, "flip": 0}, {"module": 18, "dx": 63, "dy": -45, "flip": 0}, {"module": 18, "dx": 70, "dy": -105, "flip": 0}, {"module": 18, "dx": -49, "dy": -115, "flip": 0}, {"module": 18, "dx": -17, "dy": -85, "flip": 0}, {"module": 18, "dx": 11, "dy": -53, "flip": 0}, {"module": 18, "dx": -27, "dy": -68, "flip": 0}, {"module": 36, "dx": 3, "dy": -136, "flip": 0}, {"module": 36, "dx": 3, "dy": -105, "flip": 0}, {"module": 36, "dx": 3, "dy": -74, "flip": 0}, {"module": 36, "dx": -3, "dy": -136, "flip": 0}, {"module": 36, "dx": 0, "dy": -136, "flip": 0}, {"module": 36, "dx": -3, "dy": -105, "flip": 0}, {"module": 36, "dx": 0, "dy": -105, "flip": 0}, {"module": 36, "dx": -3, "dy": -74, "flip": 0}, {"module": 36, "dx": 0, "dy": -74, "flip": 0}, {"module": 37, "dx": -15, "dy": -136, "flip": 0}, {"module": 37, "dx": -15, "dy": -105, "flip": 0}, {"module": 37, "dx": -15, "dy": -74, "flip": 0}, {"module": 37, "dx": -15, "dy": -43, "flip": 0}, {"module": 37, "dx": 12, "dy": -136, "flip": 0}, {"module": 37, "dx": 12, "dy": -105, "flip": 0}, {"module": 37, "dx": 12, "dy": -74, "flip": 0}, {"module": 37, "dx": 12, "dy": -43, "flip": 0}, {"module": 6, "dx": -12, "dy": -136, "flip": 0}, {"module": 6, "dx": -12, "dy": -105, "flip": 0}, {"module": 6, "dx": -12, "dy": -74, "flip": 0}, {"module": 6, "dx": -12, "dy": -43, "flip": 0}, {"module": 6, "dx": 9, "dy": -136, "flip": 0}, {"module": 6, "dx": 9, "dy": -105, "flip": 0}, {"module": 6, "dx": 9, "dy": -74, "flip": 0}, {"module": 6, "dx": 9, "dy": -43, "flip": 0}, {"module": 29, "dx": -48, "dy": -40, "flip": 0}, {"module": 12, "dx": -29, "dy": -29, "flip": 4}, {"module": 16, "dx": -59, "dy": -81, "flip": 0}, {"module": 16, "dx": 44, "dy": -92, "flip": 0}, {"module": 16, "dx": -29, "dy": -99, "flip": 0}], [{"module": 1, "dx": -24, "dy": -43, "flip": 0}, {"module": 1, "dx": 15, "dy": -43, "flip": 4}, {"module": 1, "dx": -24, "dy": -74, "flip": 0}, {"module": 1, "dx": 15, "dy": -74, "flip": 4}, {"module": 18, "dx": -46, "dy": -36, "flip": 0}, {"module": 18, "dx": -30, "dy": -27, "flip": 0}, {"module": 18, "dx": -42, "dy": -13, "flip": 0}, {"module": 18, "dx": -31, "dy": -16, "flip": 0}, {"module": 18, "dx": -11, "dy": -17, "flip": 0}, {"module": 18, "dx": -23, "dy": -42, "flip": 0}, {"module": 18, "dx": 13, "dy": -37, "flip": 0}, {"module": 18, "dx": 41, "dy": -111, "flip": 0}, {"module": 18, "dx": 32, "dy": -31, "flip": 0}, {"module": 18, "dx": 28, "dy": -25, "flip": 0}, {"module": 18, "dx": 22, "dy": -7, "flip": 0}, {"module": 18, "dx": 70, "dy": -77, "flip": 0}, {"module": 18, "dx": 37, "dy": -4, "flip": 0}, {"module": 37, "dx": -15, "dy": -74, "flip": 0}, {"module": 37, "dx": -15, "dy": -43, "flip": 0}, {"module": 6, "dx": -12, "dy": -74, "flip": 0}, {"module": 6, "dx": -12, "dy": -43, "flip": 0}, {"module": 37, "dx": 12, "dy": -74, "flip": 0}, {"module": 37, "dx": 12, "dy": -43, "flip": 0}, {"module": 6, "dx": 9, "dy": -74, "flip": 0}, {"module": 6, "dx": 9, "dy": -43, "flip": 0}, {"module": 36, "dx": -9, "dy": -74, "flip": 0}, {"module": 36, "dx": -9, "dy": -43, "flip": 0}, {"module": 36, "dx": 6, "dy": -74, "flip": 0}, {"module": 36, "dx": 6, "dy": -43, "flip": 0}, {"module": 36, "dx": -6, "dy": -74, "flip": 0}, {"module": 36, "dx": 3, "dy": -74, "flip": 0}, {"module": 36, "dx": 3, "dy": -43, "flip": 0}, {"module": 36, "dx": -6, "dy": -43, "flip": 0}, {"module": 36, "dx": 0, "dy": -43, "flip": 0}, {"module": 36, "dx": -3, "dy": -74, "flip": 0}, {"module": 36, "dx": -3, "dy": -43, "flip": 0}, {"module": 29, "dx": -48, "dy": -40, "flip": 0}, {"module": 12, "dx": -29, "dy": -29, "flip": 4}, {"module": 1, "dx": -24, "dy": -105, "flip": 0}, {"module": 1, "dx": 15, "dy": -105, "flip": 4}, {"module": 37, "dx": -15, "dy": -105, "flip": 0}, {"module": 6, "dx": -12, "dy": -105, "flip": 0}, {"module": 37, "dx": 12, "dy": -105, "flip": 0}, {"module": 6, "dx": 9, "dy": -105, "flip": 0}, {"module": 36, "dx": -9, "dy": -105, "flip": 0}, {"module": 36, "dx": 6, "dy": -105, "flip": 0}, {"module": 36, "dx": -6, "dy": -105, "flip": 0}, {"module": 36, "dx": 3, "dy": -105, "flip": 0}, {"module": 36, "dx": -3, "dy": -105, "flip": 0}, {"module": 1, "dx": -24, "dy": -136, "flip": 0}, {"module": 1, "dx": 15, "dy": -136, "flip": 4}, {"module": 37, "dx": -15, "dy": -136, "flip": 0}, {"module": 6, "dx": -12, "dy": -136, "flip": 0}, {"module": 37, "dx": 12, "dy": -136, "flip": 0}, {"module": 6, "dx": 9, "dy": -136, "flip": 0}, {"module": 36, "dx": -9, "dy": -136, "flip": 0}, {"module": 36, "dx": 6, "dy": -136, "flip": 0}, {"module": 36, "dx": -6, "dy": -136, "flip": 0}, {"module": 36, "dx": 3, "dy": -136, "flip": 0}, {"module": 36, "dx": -3, "dy": -136, "flip": 0}, {"module": 18, "dx": -32, "dy": -85, "flip": 0}, {"module": 18, "dx": -62, "dy": -86, "flip": 0}, {"module": 18, "dx": 31, "dy": -62, "flip": 0}, {"module": 18, "dx": 63, "dy": -45, "flip": 0}, {"module": 18, "dx": 69, "dy": -89, "flip": 0}, {"module": 18, "dx": -42, "dy": -96, "flip": 0}, {"module": 18, "dx": -14, "dy": -85, "flip": 0}, {"module": 18, "dx": 8, "dy": -53, "flip": 0}, {"module": 18, "dx": -57, "dy": -52, "flip": 0}, {"module": 36, "dx": 0, "dy": -136, "flip": 0}, {"module": 36, "dx": 0, "dy": -105, "flip": 0}, {"module": 36, "dx": 0, "dy": -74, "flip": 0}, {"module": 13, "dx": -38, "dy": -120, "flip": 0}, {"module": 13, "dx": 32, "dy": -105, "flip": 0}, {"module": 13, "dx": -63, "dy": -89, "flip": 0}], [{"module": 1, "dx": -22, "dy": -43, "flip": 0}, {"module": 1, "dx": 14, "dy": -43, "flip": 4}, {"module": 1, "dx": -22, "dy": -74, "flip": 0}, {"module": 1, "dx": 14, "dy": -74, "flip": 4}, {"module": 18, "dx": -55, "dy": -48, "flip": 0}, {"module": 18, "dx": -28, "dy": -27, "flip": 0}, {"module": 18, "dx": -51, "dy": -17, "flip": 0}, {"module": 18, "dx": -29, "dy": -16, "flip": 0}, {"module": 18, "dx": -9, "dy": -17, "flip": 0}, {"module": 18, "dx": -37, "dy": -67, "flip": 0}, {"module": 18, "dx": 12, "dy": -37, "flip": 0}, {"module": 18, "dx": 32, "dy": -58, "flip": 0}, {"module": 18, "dx": 47, "dy": -26, "flip": 0}, {"module": 18, "dx": 27, "dy": -25, "flip": 0}, {"module": 18, "dx": 21, "dy": -7, "flip": 0}, {"module": 18, "dx": 57, "dy": -46, "flip": 0}, {"module": 18, "dx": 43, "dy": -10, "flip": 0}, {"module": 37, "dx": -13, "dy": -74, "flip": 0}, {"module": 37, "dx": -13, "dy": -43, "flip": 0}, {"module": 6, "dx": -10, "dy": -74, "flip": 0}, {"module": 6, "dx": -10, "dy": -43, "flip": 0}, {"module": 37, "dx": 11, "dy": -74, "flip": 0}, {"module": 37, "dx": 11, "dy": -43, "flip": 0}, {"module": 6, "dx": 8, "dy": -74, "flip": 0}, {"module": 6, "dx": 8, "dy": -43, "flip": 0}, {"module": 36, "dx": -7, "dy": -74, "flip": 0}, {"module": 36, "dx": -7, "dy": -43, "flip": 0}, {"module": 36, "dx": 5, "dy": -74, "flip": 0}, {"module": 36, "dx": 5, "dy": -43, "flip": 0}, {"module": 36, "dx": -4, "dy": -74, "flip": 0}, {"module": 36, "dx": 2, "dy": -74, "flip": 0}, {"module": 36, "dx": 2, "dy": -43, "flip": 0}, {"module": 36, "dx": -4, "dy": -43, "flip": 0}, {"module": 36, "dx": -1, "dy": -74, "flip": 0}, {"module": 36, "dx": -1, "dy": -43, "flip": 0}, {"module": 12, "dx": -28, "dy": -34, "flip": 4}, {"module": 1, "dx": -22, "dy": -105, "flip": 0}, {"module": 1, "dx": 14, "dy": -105, "flip": 4}, {"module": 37, "dx": -13, "dy": -105, "flip": 0}, {"module": 6, "dx": -10, "dy": -105, "flip": 0}, {"module": 37, "dx": 11, "dy": -105, "flip": 0}, {"module": 6, "dx": 8, "dy": -105, "flip": 0}, {"module": 36, "dx": -7, "dy": -105, "flip": 0}, {"module": 36, "dx": 5, "dy": -105, "flip": 0}, {"module": 36, "dx": -4, "dy": -105, "flip": 0}, {"module": 36, "dx": 2, "dy": -105, "flip": 0}, {"module": 36, "dx": -1, "dy": -105, "flip": 0}, {"module": 1, "dx": -22, "dy": -136, "flip": 0}, {"module": 1, "dx": 14, "dy": -136, "flip": 4}, {"module": 37, "dx": -13, "dy": -136, "flip": 0}, {"module": 6, "dx": -10, "dy": -136, "flip": 0}, {"module": 37, "dx": 11, "dy": -136, "flip": 0}, {"module": 6, "dx": 8, "dy": -136, "flip": 0}, {"module": 36, "dx": -7, "dy": -136, "flip": 0}, {"module": 36, "dx": 5, "dy": -136, "flip": 0}, {"module": 36, "dx": -4, "dy": -136, "flip": 0}, {"module": 36, "dx": 2, "dy": -136, "flip": 0}, {"module": 36, "dx": -1, "dy": -136, "flip": 0}, {"module": 30, "dx": 26, "dy": -116, "flip": 0}, {"module": 30, "dx": -39, "dy": -136, "flip": 0}, {"module": 30, "dx": -60, "dy": -99, "flip": 0}], [{"module": 15, "dx": -15, "dy": -35, "flip": 0}], [{"module": 22, "dx": -35, "dy": -43, "flip": 0}, {"module": 22, "dx": 0, "dy": -43, "flip": 4}], [{"module": 23, "dx": -51, "dy": -56, "flip": 0}, {"module": 23, "dx": 0, "dy": -56, "flip": 4}], [{"module": 27, "dx": -60, "dy": -69, "flip": 0}, {"module": 27, "dx": 0, "dy": -69, "flip": 4}], [{"module": 31, "dx": -29, "dy": -74, "flip": 0}], [{"module": 32, "dx": -52, "dy": -73, "flip": 0}], [{"module": 33, "dx": -58, "dy": -56, "flip": 0}], [{"module": 34, "dx": -62, "dy": -39, "flip": 0}], [{"module": 14, "dx": -88, "dy": -133, "flip": 0}, {"module": 14, "dx": -89, "dy": -89, "flip": 2}, {"module": 14, "dx": -53, "dy": -56, "flip": 0}], [{"module": 14, "dx": -83, "dy": -127, "flip": 0}, {"module": 14, "dx": -84, "dy": -83, "flip": 2}, {"module": 14, "dx": -48, "dy": -50, "flip": 0}], [{"module": 14, "dx": -80, "dy": -116, "flip": 0}, {"module": 14, "dx": -81, "dy": -72, "flip": 2}, {"module": 14, "dx": -45, "dy": -39, "flip": 0}, {"module": 14, "dx": -63, "dy": -142, "flip": 4}], [{"module": 14, "dx": -69, "dy": -103, "flip": 0}, {"module": 14, "dx": -70, "dy": -59, "flip": 2}, {"module": 14, "dx": -34, "dy": -26, "flip": 0}, {"module": 14, "dx": -52, "dy": -129, "flip": 4}], [{"module": 14, "dx": -61, "dy": -96, "flip": 0}, {"module": 14, "dx": -62, "dy": -52, "flip": 2}, {"module": 14, "dx": -26, "dy": -19, "flip": 0}, {"module": 14, "dx": -44, "dy": -122, "flip": 4}, {"module": 14, "dx": -98, "dy": -149, "flip": 0}], [{"module": 24, "dx": -23, "dy": -40, "flip": 0}, {"module": 14, "dx": -88, "dy": -133, "flip": 0}, {"module": 14, "dx": -89, "dy": -89, "flip": 2}, {"module": 14, "dx": -53, "dy": -56, "flip": 0}], [{"module": 24, "dx": -23, "dy": -40, "flip": 0}, {"module": 14, "dx": -83, "dy": -127, "flip": 0}, {"module": 14, "dx": -84, "dy": -83, "flip": 2}, {"module": 14, "dx": -48, "dy": -50, "flip": 0}], [{"module": 24, "dx": -23, "dy": -40, "flip": 0}, {"module": 14, "dx": -80, "dy": -116, "flip": 0}, {"module": 14, "dx": -81, "dy": -72, "flip": 2}, {"module": 14, "dx": -45, "dy": -39, "flip": 0}, {"module": 14, "dx": -63, "dy": -142, "flip": 4}], [{"module": 24, "dx": -23, "dy": -40, "flip": 0}, {"module": 14, "dx": -69, "dy": -103, "flip": 0}, {"module": 14, "dx": -70, "dy": -59, "flip": 2}, {"module": 14, "dx": -34, "dy": -26, "flip": 0}, {"module": 14, "dx": -52, "dy": -129, "flip": 4}], [{"module": 24, "dx": -23, "dy": -40, "flip": 0}, {"module": 14, "dx": -61, "dy": -96, "flip": 0}, {"module": 14, "dx": -62, "dy": -52, "flip": 2}, {"module": 14, "dx": -26, "dy": -19, "flip": 0}, {"module": 14, "dx": -44, "dy": -122, "flip": 4}, {"module": 14, "dx": -98, "dy": -149, "flip": 0}], [{"module": 14, "dx": -60, "dy": -148, "flip": 0}], [{"module": 14, "dx": -60, "dy": -128, "flip": 0}, {"module": 14, "dx": -43, "dy": -159, "flip": 4}], [{"module": 24, "dx": 29, "dy": -70, "flip": 0}, {"module": 24, "dx": -28, "dy": -61, "flip": 0}, {"module": 24, "dx": -57, "dy": -40, "flip": 0}, {"module": 24, "dx": -68, "dy": -74, "flip": 0}, {"module": 24, "dx": 4, "dy": -50, "flip": 0}, {"module": 14, "dx": -60, "dy": -98, "flip": 0}, {"module": 14, "dx": -43, "dy": -129, "flip": 4}, {"module": 14, "dx": -63, "dy": -158, "flip": 0}], [{"module": 24, "dx": 29, "dy": -70, "flip": 0}, {"module": 24, "dx": -28, "dy": -61, "flip": 0}, {"module": 24, "dx": -57, "dy": -40, "flip": 0}, {"module": 24, "dx": -68, "dy": -74, "flip": 0}, {"module": 24, "dx": 4, "dy": -50, "flip": 0}, {"module": 14, "dx": -60, "dy": -69, "flip": 0}, {"module": 14, "dx": -43, "dy": -100, "flip": 4}, {"module": 14, "dx": -63, "dy": -129, "flip": 0}, {"module": 14, "dx": -48, "dy": -158, "flip": 4}], [{"module": 24, "dx": 29, "dy": -70, "flip": 0}, {"module": 24, "dx": -28, "dy": -61, "flip": 0}, {"module": 24, "dx": -57, "dy": -40, "flip": 0}, {"module": 24, "dx": -68, "dy": -74, "flip": 0}, {"module": 24, "dx": 4, "dy": -50, "flip": 0}, {"module": 14, "dx": -60, "dy": -59, "flip": 0}, {"module": 14, "dx": -43, "dy": -90, "flip": 4}, {"module": 14, "dx": -63, "dy": -119, "flip": 0}, {"module": 14, "dx": -48, "dy": -148, "flip": 4}, {"module": 19, "dx": 13, "dy": -68, "flip": 0}, {"module": 16, "dx": 19, "dy": -74, "flip": 0}], [{"module": 24, "dx": 29, "dy": -70, "flip": 0}, {"module": 24, "dx": -28, "dy": -61, "flip": 0}, {"module": 24, "dx": -57, "dy": -40, "flip": 0}, {"module": 24, "dx": -68, "dy": -74, "flip": 0}, {"module": 24, "dx": 4, "dy": -50, "flip": 0}, {"module": 14, "dx": -60, "dy": -49, "flip": 0}, {"module": 14, "dx": -43, "dy": -80, "flip": 4}, {"module": 14, "dx": -63, "dy": -109, "flip": 0}, {"module": 14, "dx": -48, "dy": -138, "flip": 4}, {"module": 14, "dx": -44, "dy": -161, "flip": 0}, {"module": 19, "dx": -65, "dy": -77, "flip": 0}, {"module": 19, "dx": -46, "dy": -51, "flip": 0}, {"module": 16, "dx": -58, "dy": -83, "flip": 0}, {"module": 16, "dx": -39, "dy": -56, "flip": 0}, {"module": 13, "dx": 16, "dy": -87, "flip": 0}], [{"module": 24, "dx": 29, "dy": -70, "flip": 0}, {"module": 24, "dx": -28, "dy": -61, "flip": 0}, {"module": 24, "dx": -57, "dy": -40, "flip": 0}, {"module": 24, "dx": -68, "dy": -74, "flip": 0}, {"module": 24, "dx": 4, "dy": -50, "flip": 0}, {"module": 14, "dx": -60, "dy": -39, "flip": 0}, {"module": 14, "dx": -43, "dy": -70, "flip": 4}, {"module": 14, "dx": -63, "dy": -99, "flip": 0}, {"module": 14, "dx": -48, "dy": -128, "flip": 4}, {"module": 14, "dx": -44, "dy": -151, "flip": 0}, {"module": 13, "dx": -61, "dy": -95, "flip": 0}, {"module": 13, "dx": -41, "dy": -59, "flip": 0}, {"module": 30, "dx": 6, "dy": -102, "flip": 0}], [{"module": 24, "dx": 29, "dy": -70, "flip": 0}, {"module": 24, "dx": -28, "dy": -61, "flip": 0}, {"module": 24, "dx": -57, "dy": -40, "flip": 0}, {"module": 24, "dx": -68, "dy": -74, "flip": 0}, {"module": 24, "dx": 4, "dy": -50, "flip": 0}, {"module": 14, "dx": -60, "dy": -34, "flip": 0}, {"module": 14, "dx": -43, "dy": -65, "flip": 4}, {"module": 14, "dx": -63, "dy": -94, "flip": 0}, {"module": 14, "dx": -48, "dy": -123, "flip": 4}, {"module": 14, "dx": -44, "dy": -146, "flip": 0}, {"module": 14, "dx": -58, "dy": -180, "flip": 4}, {"module": 30, "dx": -62, "dy": -137, "flip": 0}, {"module": 30, "dx": -18, "dy": -87, "flip": 0}, {"module": 26, "dx": 67, "dy": -148, "flip": 0}, {"module": 20, "dx": -45, "dy": -137, "flip": 0}, {"module": 21, "dx": 89, "dy": -124, "flip": 0}, {"module": 21, "dx": -70, "dy": -131, "flip": 4}, {"module": 26, "dx": -55, "dy": -125, "flip": 4}, {"module": 26, "dx": 26, "dy": -130, "flip": 0}], [{"module": 24, "dx": 29, "dy": -70, "flip": 0}, {"module": 24, "dx": -62, "dy": -68, "flip": 0}, {"module": 14, "dx": -55, "dy": -192, "flip": 4}, {"module": 26, "dx": 93, "dy": -152, "flip": 0}, {"module": 20, "dx": -54, "dy": -124, "flip": 0}, {"module": 21, "dx": 89, "dy": -109, "flip": 0}, {"module": 21, "dx": -66, "dy": -95, "flip": 4}, {"module": 26, "dx": -52, "dy": -158, "flip": 4}, {"module": 26, "dx": 58, "dy": -114, "flip": 0}, {"module": 24, "dx": -17, "dy": -53, "flip": 0}, {"module": 24, "dx": -38, "dy": -114, "flip": 0}, {"module": 20, "dx": 7, "dy": -147, "flip": 0}, {"module": 2, "dx": -14, "dy": -123, "flip": 0}, {"module": 2, "dx": 12, "dy": -113, "flip": 0}, {"module": 2, "dx": -2, "dy": -94, "flip": 0}, {"module": 2, "dx": 20, "dy": -78, "flip": 0}], [{"module": 14, "dx": -48, "dy": 25, "flip": 4}, {"module": 14, "dx": -79, "dy": -9, "flip": 0}, {"module": 14, "dx": -14, "dy": -47, "flip": 0}, {"module": 14, "dx": -127, "dy": -82, "flip": 4}, {"module": 14, "dx": -43, "dy": -101, "flip": 4}, {"module": 14, "dx": -110, "dy": -128, "flip": 0}, {"module": 14, "dx": -60, "dy": -153, "flip": 4}, {"module": 14, "dx": -61, "dy": -180, "flip": 0}, {"module": 0, "dx": 16, "dy": -101, "flip": 0}], [{"module": 14, "dx": -48, "dy": 40, "flip": 4}, {"module": 14, "dx": -79, "dy": 6, "flip": 0}, {"module": 14, "dx": -14, "dy": -32, "flip": 0}, {"module": 14, "dx": -127, "dy": -67, "flip": 4}, {"module": 14, "dx": -43, "dy": -86, "flip": 4}, {"module": 14, "dx": -110, "dy": -113, "flip": 0}, {"module": 14, "dx": -60, "dy": -138, "flip": 4}, {"module": 14, "dx": -61, "dy": -165, "flip": 0}, {"module": 0, "dx": -8, "dy": -81, "flip": 0}, {"module": 14, "dx": -118, "dy": -192, "flip": 0}], [{"module": 14, "dx": -48, "dy": 55, "flip": 4}, {"module": 14, "dx": -79, "dy": 21, "flip": 0}, {"module": 14, "dx": -14, "dy": -17, "flip": 0}, {"module": 14, "dx": -127, "dy": -52, "flip": 4}, {"module": 14, "dx": -43, "dy": -71, "flip": 4}, {"module": 14, "dx": -110, "dy": -98, "flip": 0}, {"module": 14, "dx": -60, "dy": -123, "flip": 4}, {"module": 14, "dx": -61, "dy": -150, "flip": 0}, {"module": 0, "dx": -22, "dy": -59, "flip": 0}, {"module": 14, "dx": -118, "dy": -177, "flip": 0}], [{"module": 15, "dx": -10, "dy": -13, "flip": 0}, {"module": 17, "dx": -39, "dy": -19, "flip": 0}, {"module": 17, "dx": -44, "dy": -46, "flip": 0}, {"module": 17, "dx": 24, "dy": -20, "flip": 0}, {"module": 17, "dx": 32, "dy": -37, "flip": 0}, {"module": 18, "dx": 44, "dy": -54, "flip": 0}, {"module": 18, "dx": 44, "dy": -38, "flip": 0}, {"module": 18, "dx": 51, "dy": -33, "flip": 0}, {"module": 18, "dx": 40, "dy": -19, "flip": 0}, {"module": 18, "dx": -9, "dy": -35, "flip": 0}, {"module": 18, "dx": -24, "dy": -25, "flip": 0}, {"module": 18, "dx": -43, "dy": -27, "flip": 0}, {"module": 18, "dx": -35, "dy": -63, "flip": 0}], [{"module": 15, "dx": -11, "dy": -43, "flip": 0}, {"module": 17, "dx": -21, "dy": -79, "flip": 0}, {"module": 17, "dx": -36, "dy": -42, "flip": 0}, {"module": 17, "dx": 36, "dy": -40, "flip": 0}, {"module": 17, "dx": 25, "dy": -68, "flip": 0}, {"module": 18, "dx": 29, "dy": -75, "flip": 0}, {"module": 18, "dx": 35, "dy": -54, "flip": 0}, {"module": 18, "dx": 42, "dy": -22, "flip": 0}, {"module": 18, "dx": -40, "dy": -27, "flip": 0}, {"module": 18, "dx": -3, "dy": -72, "flip": 0}, {"module": 18, "dx": -16, "dy": -46, "flip": 0}, {"module": 18, "dx": -16, "dy": -37, "flip": 0}, {"module": 18, "dx": -19, "dy": -62, "flip": 0}, {"module": 18, "dx": 19, "dy": -14, "flip": 0}], [{"module": 15, "dx": -11, "dy": -85, "flip": 0}, {"module": 17, "dx": -43, "dy": -102, "flip": 0}, {"module": 17, "dx": -33, "dy": -80, "flip": 0}, {"module": 17, "dx": 40, "dy": -103, "flip": 0}, {"module": 17, "dx": 27, "dy": -78, "flip": 0}, {"module": 18, "dx": 55, "dy": -84, "flip": 0}, {"module": 18, "dx": 44, "dy": -68, "flip": 0}, {"module": 18, "dx": 49, "dy": -54, "flip": 0}, {"module": 18, "dx": -39, "dy": -48, "flip": 0}, {"module": 18, "dx": -45, "dy": -82, "flip": 0}, {"module": 18, "dx": -34, "dy": -62, "flip": 0}, {"module": 18, "dx": -19, "dy": -64, "flip": 0}, {"module": 18, "dx": -22, "dy": -98, "flip": 0}, {"module": 18, "dx": -20, "dy": -36, "flip": 0}], [{"module": 15, "dx": -15, "dy": -112, "flip": 0}, {"module": 17, "dx": -36, "dy": -111, "flip": 0}, {"module": 17, "dx": -24, "dy": -120, "flip": 0}, {"module": 17, "dx": 43, "dy": -121, "flip": 0}, {"module": 17, "dx": 21, "dy": -115, "flip": 0}, {"module": 18, "dx": 54, "dy": -111, "flip": 0}, {"module": 18, "dx": 39, "dy": -107, "flip": 0}, {"module": 18, "dx": 25, "dy": -92, "flip": 0}, {"module": 18, "dx": -12, "dy": -55, "flip": 0}, {"module": 18, "dx": -23, "dy": -99, "flip": 0}, {"module": 18, "dx": -32, "dy": -89, "flip": 0}, {"module": 18, "dx": -21, "dy": -74, "flip": 0}, {"module": 18, "dx": -43, "dy": -118, "flip": 0}, {"module": 18, "dx": 12, "dy": -65, "flip": 0}], [{"module": 15, "dx": -15, "dy": -129, "flip": 0}, {"module": 17, "dx": -36, "dy": -128, "flip": 0}, {"module": 17, "dx": -24, "dy": -137, "flip": 0}, {"module": 17, "dx": 43, "dy": -138, "flip": 0}, {"module": 17, "dx": 21, "dy": -132, "flip": 0}, {"module": 18, "dx": 54, "dy": -128, "flip": 0}, {"module": 18, "dx": 39, "dy": -124, "flip": 0}, {"module": 18, "dx": 25, "dy": -109, "flip": 0}, {"module": 18, "dx": -12, "dy": -72, "flip": 0}, {"module": 18, "dx": -23, "dy": -116, "flip": 0}, {"module": 18, "dx": -32, "dy": -106, "flip": 0}, {"module": 18, "dx": -21, "dy": -91, "flip": 0}, {"module": 18, "dx": -43, "dy": -135, "flip": 0}, {"module": 18, "dx": 12, "dy": -82, "flip": 0}, {"module": 24, "dx": 16, "dy": -44, "flip": 0}, {"module": 24, "dx": -58, "dy": -35, "flip": 0}, {"module": 24, "dx": 1, "dy": -29, "flip": 0}, {"module": 24, "dx": -29, "dy": -23, "flip": 0}], [{"module": 24, "dx": 16, "dy": -44, "flip": 0}, {"module": 24, "dx": -58, "dy": -35, "flip": 0}, {"module": 24, "dx": 1, "dy": -29, "flip": 0}, {"module": 24, "dx": -29, "dy": -23, "flip": 0}], [{"module": 24, "dx": 16, "dy": -44, "flip": 0}, {"module": 24, "dx": -58, "dy": -35, "flip": 0}, {"module": 24, "dx": 1, "dy": -29, "flip": 0}, {"module": 24, "dx": -29, "dy": -23, "flip": 0}, {"module": 36, "dx": 0, "dy": -145, "flip": 0}, {"module": 6, "dx": -3, "dy": -145, "flip": 0}, {"module": 37, "dx": 3, "dy": -145, "flip": 0}, {"module": 37, "dx": -6, "dy": -145, "flip": 0}, {"module": 37, "dx": 6, "dy": -145, "flip": 0}, {"module": 1, "dx": -15, "dy": -145, "flip": 0}, {"module": 1, "dx": 9, "dy": -145, "flip": 4}, {"module": 36, "dx": 0, "dy": -114, "flip": 0}, {"module": 6, "dx": -3, "dy": -114, "flip": 0}, {"module": 37, "dx": 3, "dy": -114, "flip": 0}, {"module": 37, "dx": -6, "dy": -114, "flip": 0}, {"module": 37, "dx": 6, "dy": -114, "flip": 0}, {"module": 1, "dx": -15, "dy": -114, "flip": 0}, {"module": 1, "dx": 9, "dy": -114, "flip": 4}], [{"module": 24, "dx": 16, "dy": -44, "flip": 0}, {"module": 24, "dx": -58, "dy": -35, "flip": 0}, {"module": 24, "dx": 1, "dy": -29, "flip": 0}, {"module": 24, "dx": -29, "dy": -23, "flip": 0}, {"module": 36, "dx": 0, "dy": -110, "flip": 0}, {"module": 6, "dx": -3, "dy": -110, "flip": 0}, {"module": 37, "dx": 3, "dy": -110, "flip": 0}, {"module": 37, "dx": -6, "dy": -110, "flip": 0}, {"module": 37, "dx": 6, "dy": -110, "flip": 0}, {"module": 1, "dx": -15, "dy": -110, "flip": 0}, {"module": 1, "dx": 9, "dy": -110, "flip": 4}, {"module": 36, "dx": 0, "dy": -79, "flip": 0}, {"module": 6, "dx": -3, "dy": -79, "flip": 0}, {"module": 37, "dx": 3, "dy": -79, "flip": 0}, {"module": 37, "dx": -6, "dy": -79, "flip": 0}, {"module": 37, "dx": 6, "dy": -79, "flip": 0}, {"module": 1, "dx": -15, "dy": -79, "flip": 0}, {"module": 1, "dx": 9, "dy": -79, "flip": 4}, {"module": 36, "dx": 33, "dy": -116, "flip": 0}, {"module": 6, "dx": 30, "dy": -116, "flip": 0}, {"module": 37, "dx": 36, "dy": -116, "flip": 0}, {"module": 37, "dx": 27, "dy": -116, "flip": 0}, {"module": 37, "dx": 39, "dy": -116, "flip": 0}, {"module": 1, "dx": 18, "dy": -116, "flip": 0}, {"module": 1, "dx": 42, "dy": -116, "flip": 4}, {"module": 36, "dx": -33, "dy": -116, "flip": 0}, {"module": 6, "dx": -36, "dy": -116, "flip": 0}, {"module": 37, "dx": -30, "dy": -116, "flip": 0}, {"module": 37, "dx": -39, "dy": -116, "flip": 0}, {"module": 37, "dx": -27, "dy": -116, "flip": 0}, {"module": 1, "dx": -48, "dy": -116, "flip": 0}, {"module": 1, "dx": -24, "dy": -116, "flip": 4}], [{"module": 36, "dx": 0, "dy": -63, "flip": 0}, {"module": 6, "dx": -3, "dy": -63, "flip": 0}, {"module": 37, "dx": 3, "dy": -63, "flip": 0}, {"module": 37, "dx": -6, "dy": -63, "flip": 0}, {"module": 37, "dx": 6, "dy": -63, "flip": 0}, {"module": 1, "dx": -15, "dy": -63, "flip": 0}, {"module": 1, "dx": 9, "dy": -63, "flip": 4}, {"module": 36, "dx": 0, "dy": -32, "flip": 0}, {"module": 6, "dx": -3, "dy": -32, "flip": 0}, {"module": 37, "dx": 3, "dy": -32, "flip": 0}, {"module": 37, "dx": -6, "dy": -32, "flip": 0}, {"module": 37, "dx": 6, "dy": -32, "flip": 0}, {"module": 1, "dx": -15, "dy": -32, "flip": 0}, {"module": 1, "dx": 9, "dy": -32, "flip": 4}, {"module": 36, "dx": 33, "dy": -53, "flip": 0}, {"module": 6, "dx": 30, "dy": -53, "flip": 0}, {"module": 37, "dx": 36, "dy": -53, "flip": 0}, {"module": 37, "dx": 27, "dy": -53, "flip": 0}, {"module": 37, "dx": 39, "dy": -53, "flip": 0}, {"module": 1, "dx": 18, "dy": -53, "flip": 0}, {"module": 1, "dx": 42, "dy": -53, "flip": 4}, {"module": 36, "dx": -33, "dy": -44, "flip": 0}, {"module": 6, "dx": -36, "dy": -44, "flip": 0}, {"module": 37, "dx": -30, "dy": -44, "flip": 0}, {"module": 37, "dx": -39, "dy": -44, "flip": 0}, {"module": 37, "dx": -27, "dy": -44, "flip": 0}, {"module": 1, "dx": -48, "dy": -44, "flip": 0}, {"module": 36, "dx": 0, "dy": -94, "flip": 0}, {"module": 6, "dx": -3, "dy": -94, "flip": 0}, {"module": 37, "dx": 3, "dy": -94, "flip": 0}, {"module": 37, "dx": -6, "dy": -94, "flip": 0}, {"module": 37, "dx": 6, "dy": -94, "flip": 0}, {"module": 1, "dx": -15, "dy": -94, "flip": 0}, {"module": 1, "dx": 9, "dy": -94, "flip": 4}, {"module": 36, "dx": -33, "dy": -75, "flip": 0}, {"module": 6, "dx": -36, "dy": -75, "flip": 0}, {"module": 37, "dx": -30, "dy": -75, "flip": 0}, {"module": 37, "dx": -39, "dy": -75, "flip": 0}, {"module": 37, "dx": -27, "dy": -75, "flip": 0}, {"module": 1, "dx": -48, "dy": -75, "flip": 0}, {"module": 1, "dx": -24, "dy": -75, "flip": 4}, {"module": 1, "dx": -24, "dy": -44, "flip": 4}, {"module": 24, "dx": 16, "dy": -44, "flip": 0}, {"module": 24, "dx": -58, "dy": -35, "flip": 0}, {"module": 24, "dx": 1, "dy": -29, "flip": 0}, {"module": 24, "dx": -29, "dy": -23, "flip": 0}, {"module": 36, "dx": -33, "dy": -106, "flip": 0}, {"module": 6, "dx": -36, "dy": -106, "flip": 0}, {"module": 37, "dx": -30, "dy": -106, "flip": 0}, {"module": 37, "dx": -39, "dy": -106, "flip": 0}, {"module": 37, "dx": -27, "dy": -106, "flip": 0}, {"module": 1, "dx": -48, "dy": -106, "flip": 0}, {"module": 1, "dx": -24, "dy": -106, "flip": 4}, {"module": 36, "dx": 33, "dy": -84, "flip": 0}, {"module": 6, "dx": 30, "dy": -84, "flip": 0}, {"module": 37, "dx": 36, "dy": -84, "flip": 0}, {"module": 37, "dx": 27, "dy": -84, "flip": 0}, {"module": 37, "dx": 39, "dy": -84, "flip": 0}, {"module": 1, "dx": 18, "dy": -84, "flip": 0}, {"module": 1, "dx": 42, "dy": -84, "flip": 4}, {"module": 36, "dx": 33, "dy": -115, "flip": 0}, {"module": 6, "dx": 30, "dy": -115, "flip": 0}, {"module": 37, "dx": 36, "dy": -115, "flip": 0}, {"module": 37, "dx": 27, "dy": -115, "flip": 0}, {"module": 37, "dx": 39, "dy": -115, "flip": 0}, {"module": 1, "dx": 18, "dy": -115, "flip": 0}, {"module": 1, "dx": 42, "dy": -115, "flip": 4}, {"module": 28, "dx": 36, "dy": -70, "flip": 1}, {"module": 28, "dx": -45, "dy": -62, "flip": 1}], [{"module": 36, "dx": 0, "dy": -63, "flip": 0}, {"module": 37, "dx": -3, "dy": -63, "flip": 0}, {"module": 37, "dx": 3, "dy": -63, "flip": 0}, {"module": 1, "dx": -12, "dy": -63, "flip": 0}, {"module": 1, "dx": 6, "dy": -63, "flip": 4}, {"module": 36, "dx": 0, "dy": -32, "flip": 0}, {"module": 37, "dx": -3, "dy": -32, "flip": 0}, {"module": 37, "dx": 3, "dy": -32, "flip": 0}, {"module": 1, "dx": -12, "dy": -32, "flip": 0}, {"module": 1, "dx": 6, "dy": -32, "flip": 4}, {"module": 36, "dx": 33, "dy": -53, "flip": 0}, {"module": 37, "dx": 30, "dy": -53, "flip": 0}, {"module": 37, "dx": 36, "dy": -53, "flip": 0}, {"module": 1, "dx": 21, "dy": -53, "flip": 0}, {"module": 1, "dx": 39, "dy": -53, "flip": 4}, {"module": 36, "dx": -33, "dy": -44, "flip": 0}, {"module": 6, "dx": -36, "dy": -44, "flip": 0}, {"module": 37, "dx": -30, "dy": -44, "flip": 0}, {"module": 1, "dx": -45, "dy": -44, "flip": 0}, {"module": 36, "dx": 0, "dy": -94, "flip": 0}, {"module": 37, "dx": -3, "dy": -94, "flip": 0}, {"module": 37, "dx": 3, "dy": -94, "flip": 0}, {"module": 1, "dx": -12, "dy": -94, "flip": 0}, {"module": 1, "dx": 6, "dy": -94, "flip": 4}, {"module": 36, "dx": -33, "dy": -75, "flip": 0}, {"module": 6, "dx": -36, "dy": -75, "flip": 0}, {"module": 37, "dx": -30, "dy": -75, "flip": 0}, {"module": 1, "dx": -45, "dy": -75, "flip": 0}, {"module": 1, "dx": -27, "dy": -75, "flip": 4}, {"module": 1, "dx": -27, "dy": -44, "flip": 4}, {"module": 24, "dx": 16, "dy": -44, "flip": 0}, {"module": 24, "dx": -58, "dy": -35, "flip": 0}, {"module": 24, "dx": 1, "dy": -29, "flip": 0}, {"module": 24, "dx": -29, "dy": -23, "flip": 0}, {"module": 36, "dx": -33, "dy": -106, "flip": 0}, {"module": 6, "dx": -36, "dy": -106, "flip": 0}, {"module": 37, "dx": -30, "dy": -106, "flip": 0}, {"module": 1, "dx": -45, "dy": -106, "flip": 0}, {"module": 1, "dx": -27, "dy": -106, "flip": 4}, {"module": 36, "dx": 33, "dy": -84, "flip": 0}, {"module": 37, "dx": 36, "dy": -84, "flip": 0}, {"module": 1, "dx": 21, "dy": -84, "flip": 0}, {"module": 1, "dx": 39, "dy": -84, "flip": 4}, {"module": 36, "dx": 33, "dy": -115, "flip": 0}, {"module": 37, "dx": 30, "dy": -115, "flip": 0}, {"module": 37, "dx": 36, "dy": -115, "flip": 0}, {"module": 1, "dx": 21, "dy": -115, "flip": 0}, {"module": 1, "dx": 39, "dy": -115, "flip": 4}, {"module": 28, "dx": 37, "dy": -103, "flip": 1}, {"module": 28, "dx": -64, "dy": -83, "flip": 1}, {"module": 37, "dx": 30, "dy": -84, "flip": 0}]], "anims": [[{"delay": 2, "frame": 0}, {"delay": 2, "frame": 1}, {"delay": 2, "frame": 2}, {"delay": 2, "frame": 3}, {"delay": 2, "frame": 4}], [{"delay": 2, "frame": 5}, {"delay": 2, "frame": 6}, {"delay": 2, "frame": 7}, {"delay": 2, "frame": 8}, {"delay": 2, "frame": 9}, {"delay": 2, "frame": 10}, {"delay": 2, "frame": 11}, {"delay": 2, "frame": 12}, {"delay": 2, "frame": 13}, {"delay": 2, "frame": 14}, {"delay": 2, "frame": 15}, {"delay": 2, "frame": 16}], [{"delay": 2, "frame": 17}, {"delay": 2, "frame": 18}, {"delay": 2, "frame": 19}, {"delay": 2, "frame": 20}, {"delay": 2, "frame": 21}, {"delay": 2, "frame": 22}, {"delay": 2, "frame": 23}, {"delay": 2, "frame": 24}, {"delay": 2, "frame": 25}, {"delay": 2, "frame": 26}, {"delay": 2, "frame": 27}, {"delay": 2, "frame": 28}], [{"delay": 2, "frame": 29}, {"delay": 2, "frame": 30}, {"delay": 2, "frame": 31}, {"delay": 2, "frame": 32}, {"delay": 2, "frame": 33}, {"delay": 2, "frame": 34}, {"delay": 2, "frame": 35}, {"delay": 2, "frame": 33}, {"delay": 2, "frame": 34}, {"delay": 2, "frame": 36}, {"delay": 2, "frame": 37}, {"delay": 2, "frame": 38}, {"delay": 2, "frame": 32}], [{"delay": 2, "frame": 39}, {"delay": 2, "frame": 40}, {"delay": 2, "frame": 41}, {"delay": 2, "frame": 42}, {"delay": 2, "frame": 43}, {"delay": 2, "frame": 44}, {"delay": 2, "frame": 45}, {"delay": 2, "frame": 46}, {"delay": 2, "frame": 43}, {"delay": 2, "frame": 44}, {"delay": 2, "frame": 45}, {"delay": 2, "frame": 46}], [{"delay": 2, "frame": 47}, {"delay": 2, "frame": 48}, {"delay": 2, "frame": 49}, {"delay": 2, "frame": 50}, {"delay": 2, "frame": 51}, {"delay": 2, "frame": 52}, {"delay": 2, "frame": 53}, {"delay": 2, "frame": 54}, {"delay": 2, "frame": 55}, {"delay": 2, "frame": 56}], [{"delay": 2, "frame": 57}, {"delay": 2, "frame": 58}, {"delay": 2, "frame": 59}, {"delay": 2, "frame": 60}, {"delay": 2, "frame": 61}, {"delay": 2, "frame": 62}, {"delay": 2, "frame": 63}, {"delay": 2, "frame": 64}, {"delay": 2, "frame": 65}, {"delay": 2, "frame": 12}, {"delay": 2, "frame": 13}, {"delay": 2, "frame": 14}, {"delay": 2, "frame": 15}, {"delay": 2, "frame": 16}], [{"delay": 2, "frame": 17}, {"delay": 2, "frame": 18}, {"delay": 2, "frame": 19}, {"delay": 2, "frame": 20}, {"delay": 2, "frame": 21}, {"delay": 2, "frame": 22}, {"delay": 2, "frame": 23}, {"delay": 2, "frame": 24}, {"delay": 2, "frame": 66}, {"delay": 2, "frame": 67}, {"delay": 2, "frame": 68}, {"delay": 2, "frame": 25}, {"delay": 2, "frame": 26}, {"delay": 2, "frame": 27}, {"delay": 2, "frame": 28}], [{"delay": 2, "frame": 69}, {"delay": 2, "frame": 70}, {"delay": 2, "frame": 71}, {"delay": 2, "frame": 72}, {"delay": 2, "frame": 73}, {"delay": 2, "frame": 74}, {"delay": 2, "frame": 75}, {"delay": 2, "frame": 76}, {"delay": 2, "frame": 77}, {"delay": 2, "frame": 78}, {"delay": 2, "frame": 77}, {"delay": 2, "frame": 78}, {"delay": 2, "frame": 77}, {"delay": 2, "frame": 78}]], "hitboxes": null, "bodyboxes": null, "bytes_consumed": 9286, "bytes_total": 9286, "spr_file_id": 265, "images": [301, 302, 304]}