{"modules": [{"img": 0, "x": 0, "y": 0, "w": 40, "h": 28}, {"img": 0, "x": 45, "y": 19, "w": 16, "h": 30}, {"img": 0, "x": 61, "y": 19, "w": 15, "h": 32}, {"img": 0, "x": 40, "y": 0, "w": 30, "h": 19}, {"img": 0, "x": 0, "y": 28, "w": 5, "h": 15}, {"img": 0, "x": 5, "y": 28, "w": 14, "h": 34}, {"img": 0, "x": 19, "y": 28, "w": 14, "h": 36}, {"img": 0, "x": 33, "y": 28, "w": 12, "h": 22}], "frames": [[{"module": 1, "dx": -30, "dy": -45, "flip": 0}, {"module": 3, "dx": -14, "dy": -48, "flip": 0}, {"module": 2, "dx": 16, "dy": -41, "flip": 0}, {"module": 0, "dx": -20, "dy": -28, "flip": 0}], [{"module": 1, "dx": -30, "dy": -45, "flip": 0}, {"module": 3, "dx": -14, "dy": -48, "flip": 0}, {"module": 2, "dx": 16, "dy": -41, "flip": 0}, {"module": 0, "dx": -20, "dy": -28, "flip": 0}, {"module": 4, "dx": -2, "dy": -66, "flip": 0}], [{"module": 1, "dx": -30, "dy": -45, "flip": 0}, {"module": 3, "dx": -14, "dy": -48, "flip": 0}, {"module": 2, "dx": 16, "dy": -41, "flip": 0}, {"module": 0, "dx": -20, "dy": -28, "flip": 0}, {"module": 5, "dx": -9, "dy": -80, "flip": 0}], [{"module": 1, "dx": -30, "dy": -45, "flip": 0}, {"module": 3, "dx": -14, "dy": -48, "flip": 0}, {"module": 2, "dx": 16, "dy": -41, "flip": 0}, {"module": 0, "dx": -20, "dy": -28, "flip": 0}, {"module": 6, "dx": -10, "dy": -87, "flip": 0}], [{"module": 1, "dx": -30, "dy": -45, "flip": 0}, {"module": 3, "dx": -14, "dy": -48, "flip": 0}, {"module": 2, "dx": 16, "dy": -41, "flip": 0}, {"module": 0, "dx": -20, "dy": -28, "flip": 0}, {"module": 7, "dx": -9, "dy": -89, "flip": 0}]], "anims": [[{"delay": 1, "frame": 0}], [{"delay": 2, "frame": 1}, {"delay": 2, "frame": 2}, {"delay": 2, "frame": 3}, {"delay": 2, "frame": 4}, {"delay": 2, "frame": 0}]], "hitboxes": null, "bodyboxes": [[[-34, -91, 67, 93]], [[-34, -91, 67, 93]], [[-34, -91, 67, 93]], [[-34, -91, 67, 93]], [[-34, -91, 67, 93]]], "bytes_consumed": 380, "bytes_total": 380, "spr_file_id": 291, "images": [257]}