{"modules": [{"img": 0, "x": 0, "y": 0, "w": 25, "h": 22}, {"img": 0, "x": 48, "y": 0, "w": 19, "h": 15}, {"img": 0, "x": 55, "y": 30, "w": 7, "h": 10}, {"img": 0, "x": 47, "y": 30, "w": 7, "h": 9}, {"img": 0, "x": 47, "y": 39, "w": 6, "h": 8}, {"img": 0, "x": 25, "y": 0, "w": 23, "h": 22}, {"img": 0, "x": 48, "y": 15, "w": 18, "h": 15}, {"img": 0, "x": 36, "y": 37, "w": 11, "h": 10}, {"img": 0, "x": 25, "y": 37, "w": 11, "h": 10}, {"img": 0, "x": 1, "y": 22, "w": 24, "h": 22}, {"img": 0, "x": 25, "y": 22, "w": 20, "h": 15}], "frames": [[{"module": 0, "dx": -12, "dy": -45, "flip": 0}, {"module": 1, "dx": -9, "dy": -23, "flip": 0}, {"module": 3, "dx": -12, "dy": -26, "flip": 0}, {"module": 3, "dx": 6, "dy": -26, "flip": 4}], [{"module": 0, "dx": -12, "dy": -44, "flip": 0}, {"module": 1, "dx": -9, "dy": -22, "flip": 0}, {"module": 4, "dx": -11, "dy": -25, "flip": 0}, {"module": 4, "dx": 5, "dy": -25, "flip": 4}], [{"module": 0, "dx": -12, "dy": -46, "flip": 0}, {"module": 1, "dx": -9, "dy": -24, "flip": 0}, {"module": 4, "dx": -11, "dy": -27, "flip": 0}, {"module": 4, "dx": 5, "dy": -27, "flip": 4}], [{"module": 5, "dx": -11, "dy": -45, "flip": 0}, {"module": 6, "dx": -7, "dy": -23, "flip": 0}, {"module": 7, "dx": -12, "dy": -26, "flip": 0}], [{"module": 8, "dx": -12, "dy": -25, "flip": 0}, {"module": 5, "dx": -11, "dy": -44, "flip": 0}, {"module": 6, "dx": -7, "dy": -22, "flip": 0}], [{"module": 8, "dx": -12, "dy": -27, "flip": 0}, {"module": 5, "dx": -11, "dy": -46, "flip": 0}, {"module": 6, "dx": -7, "dy": -24, "flip": 0}], [{"module": 9, "dx": -11, "dy": -45, "flip": 0}, {"module": 10, "dx": -10, "dy": -23, "flip": 0}, {"module": 3, "dx": -12, "dy": -26, "flip": 0}, {"module": 3, "dx": 6, "dy": -26, "flip": 4}], [{"module": 9, "dx": -11, "dy": -44, "flip": 0}, {"module": 10, "dx": -10, "dy": -22, "flip": 0}, {"module": 2, "dx": -11, "dy": -25, "flip": 0}, {"module": 2, "dx": 5, "dy": -25, "flip": 4}], [{"module": 9, "dx": -11, "dy": -46, "flip": 0}, {"module": 10, "dx": -10, "dy": -24, "flip": 0}, {"module": 2, "dx": -11, "dy": -27, "flip": 0}, {"module": 2, "dx": 5, "dy": -27, "flip": 4}]], "anims": [[{"delay": 2, "frame": 0}, {"delay": 2, "frame": 1}, {"delay": 2, "frame": 0}, {"delay": 2, "frame": 2}], [{"delay": 2, "frame": 3}, {"delay": 2, "frame": 4}, {"delay": 2, "frame": 3}, {"delay": 2, "frame": 5}], [{"delay": 2, "frame": 6}, {"delay": 2, "frame": 7}, {"delay": 2, "frame": 6}, {"delay": 2, "frame": 8}]], "hitboxes": [[[-8, -8, 16, 16]], [[-8, -8, 16, 16]], [[-8, -8, 16, 16]], [[-8, -8, 16, 16]], [[-8, -8, 16, 16]], [[-8, -8, 16, 16]], [[-8, -8, 16, 16]], [[-8, -8, 16, 16]], [[-8, -8, 16, 16]]], "bodyboxes": [[[-15, -47, 31, 42]], [[-15, -47, 31, 42]], [[-15, -47, 31, 42]], [[-15, -47, 31, 42]], [[-15, -47, 31, 42]], [[-15, -47, 31, 42]], [[-15, -47, 31, 42]], [[-15, -47, 31, 42]], [[-15, -47, 31, 42]]], "bytes_consumed": 646, "bytes_total": 646, "spr_file_id": 45, "images": [133]}