{"modules": [{"img": 0, "x": 0, "y": 0, "w": 18, "h": 18}, {"img": 0, "x": 18, "y": 0, "w": 18, "h": 18}, {"img": 0, "x": 36, "y": 0, "w": 18, "h": 18}, {"img": 0, "x": 54, "y": 0, "w": 18, "h": 18}, {"img": 0, "x": 72, "y": 0, "w": 18, "h": 18}, {"img": 0, "x": 90, "y": 0, "w": 18, "h": 18}, {"img": 0, "x": 108, "y": 0, "w": 18, "h": 18}, {"img": 0, "x": 0, "y": 18, "w": 18, "h": 18}, {"img": 0, "x": 18, "y": 18, "w": 18, "h": 18}, {"img": 0, "x": 36, "y": 18, "w": 18, "h": 18}, {"img": 0, "x": 54, "y": 18, "w": 18, "h": 18}, {"img": 0, "x": 72, "y": 18, "w": 18, "h": 18}, {"img": 0, "x": 90, "y": 18, "w": 18, "h": 18}, {"img": 0, "x": 108, "y": 18, "w": 18, "h": 18}, {"img": 0, "x": 0, "y": 36, "w": 18, "h": 18}, {"img": 0, "x": 18, "y": 36, "w": 18, "h": 18}, {"img": 0, "x": 36, "y": 36, "w": 18, "h": 18}, {"img": 0, "x": 54, "y": 36, "w": 18, "h": 18}, {"img": 0, "x": 72, "y": 36, "w": 18, "h": 18}, {"img": 0, "x": 90, "y": 36, "w": 18, "h": 18}, {"img": 0, "x": 108, "y": 36, "w": 18, "h": 18}, {"img": 0, "x": 0, "y": 54, "w": 18, "h": 18}, {"img": 0, "x": 18, "y": 54, "w": 18, "h": 18}, {"img": 0, "x": 36, "y": 54, "w": 18, "h": 18}, {"img": 0, "x": 54, "y": 54, "w": 18, "h": 18}, {"img": 0, "x": 72, "y": 54, "w": 18, "h": 18}, {"img": 0, "x": 90, "y": 54, "w": 18, "h": 18}], "frames": [[{"module": 26, "dx": 0, "dy": 0, "flip": 0}], [{"module": 0, "dx": 0, "dy": 0, "flip": 0}], [{"module": 1, "dx": 0, "dy": 0, "flip": 0}], [{"module": 2, "dx": 0, "dy": 0, "flip": 0}], [{"module": 3, "dx": 0, "dy": 0, "flip": 0}], [{"module": 4, "dx": 0, "dy": 0, "flip": 0}], [{"module": 5, "dx": 0, "dy": 0, "flip": 0}], [{"module": 6, "dx": 0, "dy": 0, "flip": 0}], [{"module": 7, "dx": 0, "dy": 0, "flip": 0}], [{"module": 8, "dx": 0, "dy": 0, "flip": 0}], [{"module": 9, "dx": 0, "dy": 0, "flip": 0}], [{"module": 10, "dx": 0, "dy": 0, "flip": 0}], [{"module": 11, "dx": 0, "dy": 0, "flip": 0}], [{"module": 12, "dx": 0, "dy": 0, "flip": 0}], [{"module": 13, "dx": 0, "dy": 0, "flip": 0}], [{"module": 14, "dx": 0, "dy": 0, "flip": 0}], [{"module": 15, "dx": 0, "dy": 0, "flip": 0}], [{"module": 16, "dx": 0, "dy": 0, "flip": 0}], [{"module": 17, "dx": 0, "dy": 0, "flip": 0}], [{"module": 18, "dx": 0, "dy": 0, "flip": 0}], [{"module": 19, "dx": 0, "dy": 0, "flip": 0}], [{"module": 20, "dx": 0, "dy": 0, "flip": 0}], [{"module": 21, "dx": 0, "dy": 0, "flip": 0}], [{"module": 22, "dx": 0, "dy": 0, "flip": 0}], [{"module": 23, "dx": 0, "dy": 0, "flip": 0}], [{"module": 24, "dx": 0, "dy": 0, "flip": 0}], [{"module": 25, "dx": 0, "dy": 0, "flip": 0}]], "anims": [], "hitboxes": null, "bodyboxes": null, "bytes_consumed": 560, "bytes_total": 560, "spr_file_id": 325, "images": [804]}