{"modules": [{"img": 0, "x": 27, "y": 38, "w": 17, "h": 16}, {"img": 0, "x": 27, "y": 54, "w": 18, "h": 16}, {"img": 0, "x": 49, "y": 0, "w": 17, "h": 16}, {"img": 0, "x": 56, "y": 71, "w": 10, "h": 4}, {"img": 0, "x": 58, "y": 58, "w": 8, "h": 3}, {"img": 0, "x": 0, "y": 0, "w": 27, "h": 18}, {"img": 0, "x": 27, "y": 0, "w": 22, "h": 19}, {"img": 0, "x": 1, "y": 36, "w": 26, "h": 20}, {"img": 0, "x": 44, "y": 38, "w": 12, "h": 10}, {"img": 0, "x": 57, "y": 38, "w": 9, "h": 8}, {"img": 0, "x": 46, "y": 49, "w": 10, "h": 10}, {"img": 0, "x": 57, "y": 47, "w": 8, "h": 9}, {"img": 0, "x": 45, "y": 60, "w": 12, "h": 8}, {"img": 0, "x": 45, "y": 69, "w": 10, "h": 9}, {"img": 0, "x": 28, "y": 70, "w": 13, "h": 8}], "frames": [[{"module": 0, "dx": -8, "dy": -19, "flip": 0}, {"module": 5, "dx": -13, "dy": -37, "flip": 0}, {"module": 14, "dx": -6, "dy": -43, "flip": 0}, {"module": 13, "dx": -15, "dy": -20, "flip": 0}, {"module": 11, "dx": 6, "dy": -20, "flip": 0}], [{"module": 0, "dx": -8, "dy": -20, "flip": 0}, {"module": 5, "dx": -13, "dy": -38, "flip": 0}, {"module": 14, "dx": -6, "dy": -44, "flip": 0}, {"module": 12, "dx": -16, "dy": -23, "flip": 0}, {"module": 9, "dx": 6, "dy": -23, "flip": 0}], [{"module": 0, "dx": -8, "dy": -18, "flip": 0}, {"module": 5, "dx": -13, "dy": -36, "flip": 0}, {"module": 14, "dx": -6, "dy": -42, "flip": 0}, {"module": 12, "dx": -16, "dy": -20, "flip": 0}, {"module": 9, "dx": 6, "dy": -20, "flip": 0}], [{"module": 1, "dx": -7, "dy": -19, "flip": 0}, {"module": 6, "dx": -9, "dy": -37, "flip": 0}, {"module": 14, "dx": -6, "dy": -43, "flip": 0}, {"module": 10, "dx": -12, "dy": -20, "flip": 0}], [{"module": 1, "dx": -7, "dy": -18, "flip": 0}, {"module": 6, "dx": -9, "dy": -36, "flip": 0}, {"module": 14, "dx": -6, "dy": -42, "flip": 0}, {"module": 8, "dx": -14, "dy": -21, "flip": 0}], [{"module": 1, "dx": -7, "dy": -19, "flip": 0}, {"module": 6, "dx": -9, "dy": -37, "flip": 0}, {"module": 14, "dx": -6, "dy": -43, "flip": 0}, {"module": 10, "dx": -12, "dy": -20, "flip": 0}], [{"module": 2, "dx": -8, "dy": -20, "flip": 0}, {"module": 7, "dx": -12, "dy": -37, "flip": 0}, {"module": 14, "dx": -6, "dy": -43, "flip": 0}, {"module": 11, "dx": 6, "dy": -22, "flip": 0}, {"module": 11, "dx": -13, "dy": -22, "flip": 4}], [{"module": 2, "dx": -8, "dy": -21, "flip": 0}, {"module": 7, "dx": -12, "dy": -38, "flip": 0}, {"module": 14, "dx": -6, "dy": -44, "flip": 0}, {"module": 9, "dx": 6, "dy": -23, "flip": 0}, {"module": 9, "dx": -14, "dy": -23, "flip": 4}], [{"module": 2, "dx": -8, "dy": -19, "flip": 0}, {"module": 7, "dx": -12, "dy": -36, "flip": 0}, {"module": 14, "dx": -6, "dy": -42, "flip": 0}, {"module": 9, "dx": 6, "dy": -21, "flip": 0}, {"module": 9, "dx": -14, "dy": -21, "flip": 4}], [{"module": 0, "dx": -8, "dy": -19, "flip": 0}, {"module": 5, "dx": -13, "dy": -37, "flip": 0}, {"module": 14, "dx": -6, "dy": -43, "flip": 0}, {"module": 13, "dx": -15, "dy": -20, "flip": 0}, {"module": 11, "dx": 6, "dy": -20, "flip": 0}, {"module": 3, "dx": -5, "dy": -23, "flip": 0}], [{"module": 1, "dx": -7, "dy": -19, "flip": 0}, {"module": 6, "dx": -9, "dy": -37, "flip": 0}, {"module": 14, "dx": -6, "dy": -43, "flip": 0}, {"module": 10, "dx": -12, "dy": -20, "flip": 0}, {"module": 4, "dx": 2, "dy": -23, "flip": 0}]], "anims": [[{"delay": 2, "frame": 0}, {"delay": 2, "frame": 1}, {"delay": 2, "frame": 0}, {"delay": 2, "frame": 2}, {"delay": 2, "frame": 9}, {"delay": 2, "frame": 1}, {"delay": 2, "frame": 0}, {"delay": 2, "frame": 2}], [{"delay": 2, "frame": 3}, {"delay": 2, "frame": 4}, {"delay": 2, "frame": 5}, {"delay": 2, "frame": 4}, {"delay": 2, "frame": 10}, {"delay": 2, "frame": 4}, {"delay": 2, "frame": 3}, {"delay": 2, "frame": 4}], [{"delay": 2, "frame": 6}, {"delay": 2, "frame": 7}, {"delay": 2, "frame": 6}, {"delay": 2, "frame": 8}]], "hitboxes": [[[-8, -8, 16, 16]], [[-8, -8, 16, 16]], [[-8, -8, 16, 16]], [[-8, -8, 16, 16]], [[-8, -8, 16, 16]], [[-8, -8, 16, 16]], [[-8, -8, 16, 16]], [[-8, -8, 16, 16]], [[-8, -8, 16, 16]], [[-8, -8, 16, 16]], [[-8, -8, 16, 16]]], "bodyboxes": [[[-16, -44, 31, 42]], [[-17, -45, 33, 42]], [[-16, -43, 31, 42]], [[-15, -44, 31, 42]], [[-16, -44, 31, 42]], [[-15, -44, 31, 42]], [[-16, -44, 31, 42]], [[-16, -45, 31, 42]], [[-16, -44, 31, 42]], [[-16, -44, 31, 42]], [[-16, -44, 31, 42]]], "bytes_consumed": 922, "bytes_total": 922, "spr_file_id": 41, "images": [130]}