{"modules": [{"img": 0, "x": 0, "y": 0, "w": 21, "h": 62}, {"img": 0, "x": 70, "y": 0, "w": 36, "h": 51}, {"img": 0, "x": 106, "y": 0, "w": 18, "h": 46}, {"img": 0, "x": 39, "y": 0, "w": 31, "h": 54}, {"img": 0, "x": 21, "y": 0, "w": 18, "h": 56}, {"img": 0, "x": 0, "y": 62, "w": 27, "h": 31}, {"img": 0, "x": 97, "y": 86, "w": 15, "h": 15}, {"img": 0, "x": 27, "y": 56, "w": 18, "h": 37}, {"img": 0, "x": 45, "y": 54, "w": 29, "h": 32}, {"img": 0, "x": 103, "y": 51, "w": 21, "h": 35}, {"img": 0, "x": 0, "y": 93, "w": 45, "h": 67}, {"img": 0, "x": 45, "y": 86, "w": 52, "h": 50}, {"img": 0, "x": 74, "y": 51, "w": 29, "h": 34}, {"img": 0, "x": 0, "y": 93, "w": 45, "h": 34}, {"img": 0, "x": 0, "y": 127, "w": 30, "h": 33}, {"img": 0, "x": 30, "y": 127, "w": 15, "h": 33}], "frames": [[{"module": 7, "dx": 109, "dy": -83, "flip": 0}, {"module": 5, "dx": 46, "dy": -81, "flip": 4}, {"module": 5, "dx": 77, "dy": -72, "flip": 4}, {"module": 5, "dx": 71, "dy": -75, "flip": 4}, {"module": 5, "dx": -73, "dy": -81, "flip": 0}, {"module": 5, "dx": -98, "dy": -74, "flip": 0}, {"module": 7, "dx": 31, "dy": -87, "flip": 4}, {"module": 7, "dx": -49, "dy": -87, "flip": 0}, {"module": 1, "dx": -36, "dy": -100, "flip": 0}, {"module": 7, "dx": -126, "dy": -83, "flip": 0}, {"module": 1, "dx": 0, "dy": -100, "flip": 4}, {"module": 0, "dx": -133, "dy": -64, "flip": 0}, {"module": 3, "dx": -113, "dy": -59, "flip": 0}, {"module": 0, "dx": -53, "dy": -64, "flip": 0}, {"module": 3, "dx": -82, "dy": -59, "flip": 4}, {"module": 8, "dx": -81, "dy": -81, "flip": 0}, {"module": 4, "dx": -33, "dy": -56, "flip": 0}, {"module": 0, "dx": 32, "dy": -64, "flip": 4}, {"module": 4, "dx": 15, "dy": -56, "flip": 4}, {"module": 0, "dx": 112, "dy": -64, "flip": 4}, {"module": 3, "dx": 51, "dy": -60, "flip": 0}, {"module": 3, "dx": 82, "dy": -60, "flip": 4}, {"module": 6, "dx": -15, "dy": -59, "flip": 0}, {"module": 6, "dx": 0, "dy": -59, "flip": 4}, {"module": 8, "dx": -33, "dy": -84, "flip": 0}, {"module": 8, "dx": 4, "dy": -83, "flip": 4}, {"module": 8, "dx": -117, "dy": -81, "flip": 0}, {"module": 8, "dx": 52, "dy": -79, "flip": 4}, {"module": 8, "dx": 91, "dy": -79, "flip": 4}], [{"module": 13, "dx": -45, "dy": -66, "flip": 0}, {"module": 14, "dx": -44, "dy": -32, "flip": 0}, {"module": 13, "dx": 0, "dy": -66, "flip": 4}, {"module": 14, "dx": 14, "dy": -32, "flip": 4}, {"module": 9, "dx": -21, "dy": -79, "flip": 0}, {"module": 9, "dx": 0, "dy": -79, "flip": 4}], [{"module": 13, "dx": -45, "dy": -66, "flip": 0}, {"module": 14, "dx": -44, "dy": -32, "flip": 0}, {"module": 13, "dx": 0, "dy": -66, "flip": 4}, {"module": 14, "dx": 14, "dy": -32, "flip": 4}, {"module": 11, "dx": -12, "dy": -101, "flip": 0}, {"module": 12, "dx": -41, "dy": -89, "flip": 0}], [{"module": 13, "dx": -45, "dy": -66, "flip": 0}, {"module": 14, "dx": -44, "dy": -32, "flip": 0}, {"module": 13, "dx": 0, "dy": -66, "flip": 4}, {"module": 14, "dx": 14, "dy": -32, "flip": 4}, {"module": 11, "dx": -40, "dy": -101, "flip": 4}, {"module": 12, "dx": 12, "dy": -89, "flip": 4}], [{"module": 15, "dx": -15, "dy": -33, "flip": 0}, {"module": 15, "dx": 0, "dy": -33, "flip": 4}]], "anims": [[{"delay": 1, "frame": 0}], [{"delay": 1, "frame": 1}], [{"delay": 1, "frame": 2}], [{"delay": 1, "frame": 3}], [{"delay": 1, "frame": 4}]], "hitboxes": null, "bodyboxes": [[[-135, -101, 269, 103]], [[-47, -80, 94, 81]], [[-47, -104, 94, 106]], [[-47, -104, 94, 106]], [[-16, -29, 32, 30]]], "bytes_consumed": 662, "bytes_total": 662, "spr_file_id": 284, "images": [261]}