{"type": "panel", "root_type": 0, "id": 0, "x": 0, "y": 0, "w": 0, "h": 0, "actions": [], "lists": [{"id": 0, "grid": true, "rows": 4, "h": 0, "i": 0, "items": [{"id": 4, "text": "UDcmd0"}, {"id": 5, "text": "UDcmd1"}, {"id": 6, "text": "UDcmd2"}, {"id": 7, "text": "UDcmd3"}], "states": [{"state": 6, "rects": [[213, 317, 43, 43, -1]]}, {"state": 19, "rects": [[257, 275, 56, 75, 6]]}, {"state": 20, "rects": [[331, 280, 70, 73, 6]]}, {"state": 21, "rects": [[413, 278, 61, 72, 6]]}, {"state": 22, "rects": [[487, 276, 76, 65, 6]]}]}], "children": [{"type": "image", "id": 1, "x": 259, "y": 342, "w": 300, "h": 18, "text": "", "anchor": 0, "pad": 0, "multiline": false, "bg_focus": 16777215, "border_focus": 0, "text_focus": 0, "spr_focus": {"action": -1, "frame": 4}, "bg": 16753920, "border": 16711680, "text_color": 32768, "spr": {"action": 82, "frame": 2}, "icon": -1, "a": -1, "b": -1}, {"type": "image", "id": 3, "x": 219, "y": 324, "w": 35, "h": 36, "text": "", "anchor": 0, "pad": 0, "multiline": false, "bg_focus": 16777215, "border_focus": 0, "text_focus": 0, "spr_focus": {"action": -1, "frame": 4}, "bg": 16753920, "border": 16711680, "text_color": 32768, "spr": {"action": 76, "frame": 2}, "icon": -1, "a": -1, "b": -1}, {"type": "image", "id": 4, "x": 256, "y": 272, "w": 57, "h": 67, "text": "", "anchor": 0, "pad": 0, "multiline": false, "bg_focus": 16777215, "border_focus": 0, "text_focus": 0, "spr_focus": {"action": -1, "frame": 4}, "bg": 16753920, "border": 16711680, "text_color": 32768, "spr": {"action": -1, "frame": 4}, "icon": -1, "a": -1, "b": -1}, {"type": "image", "id": 5, "x": 324, "y": 270, "w": 85, "h": 69, "text": "", "anchor": 0, "pad": 0, "multiline": false, "bg_focus": 16777215, "border_focus": 0, "text_focus": 0, "spr_focus": {"action": -1, "frame": 4}, "bg": 16753920, "border": 16711680, "text_color": 32768, "spr": {"action": -1, "frame": 4}, "icon": -1, "a": -1, "b": -1}, {"type": "image", "id": 6, "x": 406, "y": 283, "w": 76, "h": 56, "text": "", "anchor": 0, "pad": 0, "multiline": false, "bg_focus": 16777215, "border_focus": 0, "text_focus": 0, "spr_focus": {"action": -1, "frame": 4}, "bg": 16753920, "border": 16711680, "text_color": 32768, "spr": {"action": -1, "frame": 4}, "icon": -1, "a": -1, "b": -1}, {"type": "image", "id": 7, "x": 488, "y": 278, "w": 75, "h": 61, "text": "", "anchor": 0, "pad": 0, "multiline": false, "bg_focus": 16777215, "border_focus": 0, "text_focus": 0, "spr_focus": {"action": -1, "frame": 4}, "bg": 16753920, "border": 16711680, "text_color": 32768, "spr": {"action": -1, "frame": 4}, "icon": -1, "a": -1, "b": -1}, {"type": "image", "id": 8, "x": 258, "y": 263, "w": 48, "h": 16, "text": "L\u1ee5c H\u00e0nh \u0110i\u1ec3u", "anchor": 4, "pad": 0, "multiline": false, "bg_focus": 16777215, "border_focus": 0, "text_focus": -16777216, "spr_focus": {"action": -1, "frame": 4}, "bg": 16753920, "border": 16711680, "text_color": -16313179, "spr": {"action": -1, "frame": 4}, "icon": -1, "a": 0, "b": -1}, {"type": "image", "id": 9, "x": 333, "y": 262, "w": 64, "h": 16, "text": "H\u01b0 Kh\u00f4ng H\u00e0nh Gi\u1ea3", "anchor": 4, "pad": 0, "multiline": false, "bg_focus": 16777215, "border_focus": 0, "text_focus": -16777216, "spr_focus": {"action": -1, "frame": 4}, "bg": 16753920, "border": 16711680, "text_color": -16313179, "spr": {"action": -1, "frame": 4}, "icon": -1, "a": 0, "b": -1}, {"type": "image", "id": 10, "x": 419, "y": 262, "w": 48, "h": 16, "text": "H\u1ea3i \u00e2u", "anchor": 4, "pad": 0, "multiline": false, "bg_focus": 16777215, "border_focus": 0, "text_focus": -16777216, "spr_focus": {"action": -1, "frame": 4}, "bg": 16753920, "border": 16711680, "text_color": -16313179, "spr": {"action": -1, "frame": 4}, "icon": -1, "a": 0, "b": -1}, {"type": "image", "id": 11, "x": 497, "y": 262, "w": 48, "h": 16, "text": "Nham S\u01a1n Long", "anchor": 4, "pad": 0, "multiline": false, "bg_focus": 16777215, "border_focus": 0, "text_focus": -16777216, "spr_focus": {"action": -1, "frame": 4}, "bg": 16753920, "border": 16711680, "text_color": -16313179, "spr": {"action": -1, "frame": 4}, "icon": -1, "a": 0, "b": -1}, {"type": "image", "id": 16, "x": 272, "y": 322, "w": 23, "h": 21, "text": "", "anchor": 0, "pad": 0, "multiline": false, "bg_focus": 16777215, "border_focus": 0, "text_focus": 0, "spr_focus": {"action": -1, "frame": 4}, "bg": 16753920, "border": 16711680, "text_color": 32768, "spr": {"action": -1, "frame": 4}, "icon": -1, "a": -1, "b": -1}, {"type": "image", "id": 17, "x": 354, "y": 322, "w": 23, "h": 21, "text": "", "anchor": 0, "pad": 0, "multiline": false, "bg_focus": 16777215, "border_focus": 0, "text_focus": 0, "spr_focus": {"action": -1, "frame": 4}, "bg": 16753920, "border": 16711680, "text_color": 32768, "spr": {"action": -1, "frame": 4}, "icon": -1, "a": -1, "b": -1}, {"type": "image", "id": 18, "x": 434, "y": 322, "w": 23, "h": 21, "text": "", "anchor": 0, "pad": 0, "multiline": false, "bg_focus": 16777215, "border_focus": 0, "text_focus": 0, "spr_focus": {"action": -1, "frame": 4}, "bg": 16753920, "border": 16711680, "text_color": 32768, "spr": {"action": -1, "frame": 4}, "icon": -1, "a": -1, "b": -1}, {"type": "image", "id": 19, "x": 514, "y": 322, "w": 23, "h": 21, "text": "", "anchor": 0, "pad": 0, "multiline": false, "bg_focus": 16777215, "border_focus": 0, "text_focus": 0, "spr_focus": {"action": -1, "frame": 4}, "bg": 16753920, "border": 16711680, "text_color": 32768, "spr": {"action": -1, "frame": 4}, "icon": -1, "a": -1, "b": -1}, {"type": "image", "id": 20, "x": 569, "y": 290, "w": 70, "h": 67, "text": "", "anchor": 0, "pad": 0, "multiline": false, "bg_focus": 16777215, "border_focus": 0, "text_focus": 0, "spr_focus": {"action": -1, "frame": 4}, "bg": 16753920, "border": 16711680, "text_color": 32768, "spr": {"action": 171, "frame": 2}, "icon": -1, "a": -1, "b": -1}, {"type": "image", "id": 21, "x": 2, "y": 295, "w": 76, "h": 56, "text": "", "anchor": 0, "pad": 0, "multiline": false, "bg_focus": 16777215, "border_focus": 0, "text_focus": 0, "spr_focus": {"action": -1, "frame": 4}, "bg": 16753920, "border": 16711680, "text_color": 32768, "spr": {"action": 170, "frame": 2}, "icon": -1, "a": -1, "b": -1}], "bytes_consumed": 1045, "bytes_total": 1045}